{
  "type": "Feature",
  "properties": {
    "gn:admin1_code":"07",
    "gn:asciiname":"Terrero Blanco",
    "gn:cc2":"SV",
    "gn:country_code":"SV",
    "gn:dem":272,
    "gn:feature_class":"P",
    "gn:feature_code":"PPL",
    "gn:name":"Terrero Blanco",
    "gn:population":0,
    "gn:timezone":"America/El_Salvador",
    "iso:country":"SV",
    "name:und_x_variant":[
        "El Terrero",
        "Terrero",
        "Cerro Blanco",
        "Terrero Blanco"
    ],
    "wof:name":"Terrero Blanco",
    "wof:placetype":"locality"
},
  "geometry": {"coordinates":[-87.96250000000001,13.39861],"type":"Point"}
}