{
  "type": "Feature",
  "properties": {
    "gn:admin1_code":"05",
    "gn:asciiname":"Mogotes",
    "gn:cc2":"SV",
    "gn:country_code":"SV",
    "gn:dem":555,
    "gn:feature_class":"P",
    "gn:feature_code":"PPL",
    "gn:name":"Mogotes",
    "gn:population":0,
    "gn:timezone":"America/El_Salvador",
    "iso:country":"SV",
    "name:deu_x_preferred":[
        "Mogotes"
    ],
    "name:fra_x_preferred":[
        "Mogotes"
    ],
    "name:ita_x_preferred":[
        "Mogotes"
    ],
    "name:kat_x_preferred":[
        "\u10db\u10dd\u10d2\u10dd\u10e2\u10d4\u10e1\u10d8"
    ],
    "name:msa_x_preferred":[
        "Mogotes"
    ],
    "name:nld_x_preferred":[
        "Mogotes"
    ],
    "name:spa_x_preferred":[
        "Mogotes"
    ],
    "name:tgl_x_preferred":[
        "Mogotes"
    ],
    "name:und_x_variant":[
        "Cant\u00f3n Mogotes",
        "Los Mogotes",
        "Mogotes"
    ],
    "name:vie_x_preferred":[
        "Mogotes"
    ],
    "name:war_x_preferred":[
        "Mogotes"
    ],
    "name:zho_x_preferred":[
        "\u83ab\u6208\u7279\u65af"
    ],
    "wof:name":"Mogotes",
    "wof:placetype":"locality"
},
  "geometry": {"coordinates":[-89.39194000000001,13.97694],"type":"Point"}
}