{
  "type": "Feature",
  "properties": {
    "gn:admin1_code":"07",
    "gn:asciiname":"Bolivar",
    "gn:country_code":"SV",
    "gn:dem":176,
    "gn:feature_class":"P",
    "gn:feature_code":"PPL",
    "gn:name":"Bol\u00edvar",
    "gn:population":0,
    "gn:timezone":"America/El_Salvador",
    "iso:country":"SV",
    "name:ceb_x_preferred":[
        "Bol\u00edvar"
    ],
    "name:ita_x_preferred":[
        "Bol\u00edvar"
    ],
    "name:por_x_preferred":[
        "Bol\u00edvar"
    ],
    "name:spa_x_preferred":[
        "Bol\u00edvar"
    ],
    "name:und_x_variant":[
        "Bol\u00edvar"
    ],
    "name:zho_x_preferred":[
        "\u535a\u5229\u74e6\u723e"
    ],
    "wof:name":"Bolivar",
    "wof:placetype":"locality"
},
  "geometry": {"coordinates":[-87.95583000000001,13.57361],"type":"Point"}
}