{
  "type": "Feature",
  "properties": {
    "gn:admin1_code":"09",
    "gn:asciiname":"El Zorral",
    "gn:country_code":"SV",
    "gn:dem":191,
    "gn:feature_class":"P",
    "gn:feature_code":"PPL",
    "gn:name":"El Zorral",
    "gn:population":0,
    "gn:timezone":"America/El_Salvador",
    "iso:country":"SV",
    "wof:name":"El Zorral",
    "wof:placetype":"locality"
},
  "geometry": {"coordinates":[-88.12472,13.23722],"type":"Point"}
}