{
  "type": "Feature",
  "properties": {
    "gn:admin1_code":"03",
    "gn:asciiname":"El Conacaste",
    "gn:cc2":"SV",
    "gn:country_code":"SV",
    "gn:dem":450,
    "gn:feature_class":"P",
    "gn:feature_code":"PPL",
    "gn:name":"El Conacaste",
    "gn:population":0,
    "gn:timezone":"America/El_Salvador",
    "iso:country":"SV",
    "name:und_x_variant":[
        "Conacaste",
        "El Conacaste"
    ],
    "wof:name":"El Conacaste",
    "wof:placetype":"locality"
},
  "geometry": {"coordinates":[-88.86667,14.08333],"type":"Point"}
}