{
  "type": "Feature",
  "properties": {
    "gn:admin1_code":"07",
    "gn:asciiname":"El Caragon",
    "gn:cc2":"SV",
    "gn:country_code":"SV",
    "gn:dem":272,
    "gn:feature_class":"P",
    "gn:feature_code":"PPL",
    "gn:name":"El Carag\u00f3n",
    "gn:population":0,
    "gn:timezone":"America/El_Salvador",
    "iso:country":"SV",
    "name:und_x_variant":[
        "Caragon",
        "El Carag\u00f3n"
    ],
    "wof:name":"El Caragon",
    "wof:placetype":"locality"
},
  "geometry": {"coordinates":[-87.95,13.38333],"type":"Point"}
}