{
  "type": "Feature",
  "properties": {
    "gn:admin1_code":"09",
    "gn:asciiname":"Jalacatal",
    "gn:country_code":"SV",
    "gn:dem":214,
    "gn:feature_class":"P",
    "gn:feature_code":"PPL",
    "gn:name":"Jalacatal",
    "gn:population":0,
    "gn:timezone":"America/El_Salvador",
    "iso:country":"SV",
    "wof:name":"Jalacatal",
    "wof:placetype":"locality"
},
  "geometry": {"coordinates":[-88.22083000000001,13.495],"type":"Point"}
}