{
  "type": "Feature",
  "properties": {
    "gn:admin1_code":"07",
    "gn:asciiname":"Los Mojones",
    "gn:cc2":"SV",
    "gn:country_code":"SV",
    "gn:dem":151,
    "gn:feature_class":"P",
    "gn:feature_code":"PPL",
    "gn:name":"Los Mojones",
    "gn:population":0,
    "gn:timezone":"America/El_Salvador",
    "iso:country":"SV",
    "name:und_x_variant":[
        "Cant\u00f3n Mojones",
        "Mojones",
        "Los Mojones"
    ],
    "wof:name":"Los Mojones",
    "wof:placetype":"locality"
},
  "geometry": {"coordinates":[-87.87194000000002,13.66917],"type":"Point"}
}