{
  "type": "Feature",
  "properties": {
    "gn:admin1_code":"06",
    "gn:asciiname":"Cuyultitan",
    "gn:country_code":"SV",
    "gn:dem":370,
    "gn:feature_class":"P",
    "gn:feature_code":"PPL",
    "gn:name":"Cuyultit\u00e1n",
    "gn:population":0,
    "gn:timezone":"America/El_Salvador",
    "iso:country":"SV",
    "name:fra_x_preferred":[
        "Cuyultit\u00e1n"
    ],
    "name:ita_x_preferred":[
        "Cuyultit\u00e1n"
    ],
    "name:por_x_preferred":[
        "Cuyultit\u00e1n"
    ],
    "name:spa_x_preferred":[
        "Cuyultit\u00e1n"
    ],
    "name:zho_x_preferred":[
        "\u5eab\u5c24\u723e\u8482\u5766"
    ],
    "wof:name":"Cuyultitan",
    "wof:placetype":"locality"
},
  "geometry": {"coordinates":[-89.09778,13.54861],"type":"Point"}
}