{
  "type": "Feature",
  "properties": {
    "gn:admin1_code":"04",
    "gn:asciiname":"Piedra Labrada",
    "gn:country_code":"SV",
    "gn:dem":529,
    "gn:feature_class":"P",
    "gn:feature_code":"PPL",
    "gn:name":"Piedra Labrada",
    "gn:population":0,
    "gn:timezone":"America/El_Salvador",
    "iso:country":"SV",
    "wof:name":"Piedra Labrada",
    "wof:placetype":"locality"
},
  "geometry": {"coordinates":[-89.11667,13.85],"type":"Point"}
}