{
  "type": "Feature",
  "properties": {
    "gn:admin1_code":"01",
    "gn:asciiname":"Finca El Carmen",
    "gn:cc2":"SV",
    "gn:country_code":"SV",
    "gn:dem":1249,
    "gn:feature_class":"P",
    "gn:feature_code":"PPL",
    "gn:name":"Finca El Carmen",
    "gn:population":0,
    "gn:timezone":"America/El_Salvador",
    "iso:country":"SV",
    "name:und_x_variant":[
        "El Carmen",
        "Finca El Carmen"
    ],
    "wof:name":"Finca El Carmen",
    "wof:placetype":"locality"
},
  "geometry": {"coordinates":[-89.84999999999999,13.86667],"type":"Point"}
}