{
  "type": "Feature",
  "properties": {
    "gn:admin1_code":"05",
    "gn:asciiname":"El Conacaste",
    "gn:country_code":"SV",
    "gn:dem":833,
    "gn:feature_class":"P",
    "gn:feature_code":"PPL",
    "gn:name":"El Conacaste",
    "gn:population":0,
    "gn:timezone":"America/El_Salvador",
    "iso:country":"SV",
    "wof:name":"El Conacaste",
    "wof:placetype":"locality"
},
  "geometry": {"coordinates":[-89.35139000000002,13.6125],"type":"Point"}
}