{
  "type": "Feature",
  "properties": {
    "gn:admin1_code":"13",
    "gn:asciiname":"Tajcuilujlan",
    "gn:country_code":"SV",
    "gn:dem":825,
    "gn:feature_class":"P",
    "gn:feature_code":"PPL",
    "gn:name":"Tajcuilujl\u00e1n",
    "gn:population":0,
    "gn:timezone":"America/El_Salvador",
    "iso:country":"SV",
    "wof:name":"Tajcuilujlan",
    "wof:placetype":"locality"
},
  "geometry": {"coordinates":[-89.7075,13.82306],"type":"Point"}
}