{
  "type": "Feature",
  "properties": {
    "gn:admin1_code":"11",
    "gn:asciiname":"Valle San Felipe",
    "gn:country_code":"SV",
    "gn:dem":570,
    "gn:feature_class":"P",
    "gn:feature_code":"PPL",
    "gn:name":"Valle San Felipe",
    "gn:population":0,
    "gn:timezone":"America/El_Salvador",
    "iso:country":"SV",
    "wof:name":"Valle San Felipe",
    "wof:placetype":"locality"
},
  "geometry": {"coordinates":[-89.39278,13.97389],"type":"Point"}
}