{
  "type": "Feature",
  "properties": {
    "gn:admin1_code":"11",
    "gn:asciiname":"San Jose Las Flores",
    "gn:cc2":"SV",
    "gn:country_code":"SV",
    "gn:dem":955,
    "gn:feature_class":"P",
    "gn:feature_code":"PPL",
    "gn:name":"San Jos\u00e9 Las Flores",
    "gn:population":0,
    "gn:timezone":"America/El_Salvador",
    "iso:country":"SV",
    "name:und_x_variant":[
        "San Jose de las Flores",
        "San Jos\u00e9 Las Flores"
    ],
    "wof:name":"San Jose Las Flores",
    "wof:placetype":"locality"
},
  "geometry": {"coordinates":[-89.51083,13.86889],"type":"Point"}
}