{
  "type": "Feature",
  "properties": {
    "gn:admin1_code":"13",
    "gn:asciiname":"Hacienda Los Lagartos",
    "gn:cc2":"SV",
    "gn:country_code":"SV",
    "gn:dem":531,
    "gn:feature_class":"P",
    "gn:feature_code":"PPL",
    "gn:name":"Hacienda Los Lagartos",
    "gn:population":0,
    "gn:timezone":"America/El_Salvador",
    "iso:country":"SV",
    "name:und_x_variant":[
        "Los Lagartos",
        "Hacienda Los Lagartos"
    ],
    "wof:name":"Hacienda Los Lagartos",
    "wof:placetype":"locality"
},
  "geometry": {"coordinates":[-89.56667,13.73333],"type":"Point"}
}