{
  "type": "Feature",
  "properties": {
    "gn:admin1_code":"09",
    "gn:asciiname":"Belen",
    "gn:country_code":"SV",
    "gn:dem":571,
    "gn:feature_class":"P",
    "gn:feature_code":"PPL",
    "gn:name":"Bel\u00e9n",
    "gn:population":0,
    "gn:timezone":"America/El_Salvador",
    "iso:country":"SV",
    "name:bul_x_preferred":[
        "\u0411\u0435\u043b\u0435\u043d"
    ],
    "name:ceb_x_preferred":[
        "Belen"
    ],
    "name:hye_x_preferred":[
        "\u0532\u0565\u056c\u0565\u0576"
    ],
    "name:jpn_x_preferred":[
        "\u30d9\u30ec\u30f3"
    ],
    "name:kaz_x_preferred":[
        "\u0411\u0435\u043b\u0435\u043d"
    ],
    "name:min_x_preferred":[
        "Belen"
    ],
    "name:nld_x_preferred":[
        "Belen"
    ],
    "name:rus_x_preferred":[
        "\u0411\u0435\u043b\u0435\u043d"
    ],
    "name:sco_x_preferred":[
        "Belen"
    ],
    "name:srp_x_preferred":[
        "\u0411\u0435\u043b\u0435\u043d"
    ],
    "name:swe_x_preferred":[
        "Belen"
    ],
    "name:tur_x_preferred":[
        "Belen"
    ],
    "name:ukr_x_preferred":[
        "\u0411\u0435\u043b\u0435\u043d"
    ],
    "wof:name":"Belen",
    "wof:placetype":"locality"
},
  "geometry": {"coordinates":[-88.31667,13.76667],"type":"Point"}
}