{
  "type": "Feature",
  "properties": {
    "gn:admin1_code":"11",
    "gn:asciiname":"Caserio El Nance Dulce",
    "gn:cc2":"SV",
    "gn:country_code":"SV",
    "gn:dem":508,
    "gn:feature_class":"P",
    "gn:feature_code":"PPL",
    "gn:name":"Caser\u00edo El Nance Dulce",
    "gn:population":0,
    "gn:timezone":"America/El_Salvador",
    "iso:country":"SV",
    "name:und_x_variant":[
        "El Nance Dulce",
        "Nance Dulce",
        "Caser\u00edo El Nance Dulce"
    ],
    "wof:name":"Caserio El Nance Dulce",
    "wof:placetype":"locality"
},
  "geometry": {"coordinates":[-89.50721999999998,14.17528],"type":"Point"}
}