{
  "type": "Feature",
  "properties": {
    "gn:admin1_code":"10",
    "gn:asciiname":"San Jose Segundo",
    "gn:country_code":"SV",
    "gn:dem":709,
    "gn:feature_class":"P",
    "gn:feature_code":"PPL",
    "gn:name":"San Jos\u00e9 Segundo",
    "gn:population":0,
    "gn:timezone":"America/El_Salvador",
    "iso:country":"SV",
    "wof:name":"San Jose Segundo",
    "wof:placetype":"locality"
},
  "geometry": {"coordinates":[-89.06667,13.76667],"type":"Point"}
}