{
  "type": "Feature",
  "properties": {
    "gn:admin1_code":"01",
    "gn:asciiname":"El Tronconal",
    "gn:country_code":"SV",
    "gn:dem":1269,
    "gn:feature_class":"P",
    "gn:feature_code":"PPL",
    "gn:name":"El Tronconal",
    "gn:population":0,
    "gn:timezone":"America/El_Salvador",
    "iso:country":"SV",
    "wof:name":"El Tronconal",
    "wof:placetype":"locality"
},
  "geometry": {"coordinates":[-89.83444,13.86861],"type":"Point"}
}