{
  "type": "Feature",
  "properties": {
    "gn:admin1_code":"1.0",
    "gn:asciiname":"Lomas El Zope",
    "gn:country_code":"SV",
    "gn:dem":143,
    "gn:feature_class":"P",
    "gn:feature_code":"PPL",
    "gn:name":"Lomas El Zope",
    "gn:population":0,
    "gn:timezone":"America/El_Salvador",
    "iso:country":"SV",
    "wof:name":"Lomas El Zope",
    "wof:placetype":"locality"
},
  "geometry": {"coordinates":[-90.03528,13.91028],"type":"Point"}
}