{
  "type": "Feature",
  "properties": {
    "gn:admin1_code":"05",
    "gn:asciiname":"Loma Alta",
    "gn:country_code":"SV",
    "gn:dem":679,
    "gn:feature_class":"P",
    "gn:feature_code":"PPL",
    "gn:name":"Loma Alta",
    "gn:population":0,
    "gn:timezone":"America/El_Salvador",
    "iso:country":"SV",
    "wof:name":"Loma Alta",
    "wof:placetype":"locality"
},
  "geometry": {"coordinates":[-89.4025,13.90472],"type":"Point"}
}