{
  "type": "Feature",
  "properties": {
    "iso:country":"SV",
    "name:ceb_x_preferred":[
        "Op\u010dina Ljubljana-Be\u017eigrad"
    ],
    "name:ces_x_preferred":[
        "Be\u017eigrad"
    ],
    "name:deu_x_preferred":[
        "Be\u017eigrad"
    ],
    "name:eng_x_preferred":[
        "Be\u017eigrad"
    ],
    "name:ita_x_preferred":[
        "Distretto di Be\u017eigrad"
    ],
    "name:mkd_x_preferred":[
        "\u0411\u0435\u0436\u0438\u0433\u0440\u0430\u0434"
    ],
    "name:msa_x_preferred":[
        "Be\u017eigrad"
    ],
    "name:nld_x_preferred":[
        "Be\u017eigrad"
    ],
    "name:pol_x_preferred":[
        "Be\u017eigrad"
    ],
    "name:rup_x_preferred":[
        "Seka"
    ],
    "name:slv_x_preferred":[
        "\u010cetrtna skupnost Be\u017eigrad"
    ],
    "name:ukr_x_preferred":[
        "\u0411\u0435\u0436\u0438\u0433\u0440\u0430\u0434"
    ],
    "name:und_x_colloquial":[
        "Bezigrad"
    ],
    "name:zho_x_preferred":[
        "\u8d1d\u65e5\u683c\u52d2\u533a"
    ],
    "qs:gn_adm0_cc":"SI",
    "qs:gn_fcode":"PPL",
    "qs:gn_local":3196359,
    "qs:gn_nam_loc":"Ljubljana, Ljubljana, Ljubljana, SI",
    "qs:gn_namadm1":"12",
    "qs:gn_name":"Belgrad",
    "qs:local_max":13863,
    "qs:local_sum":25230,
    "qs:localhoods":13,
    "qs:name":"Be\u017eigrad",
    "qs:name_adm0":"Slovenija",
    "qs:name_adm1":"Ljubljana",
    "qs:name_adm2":"Ljubljana",
    "qs:name_local":"Ljubljana",
    "qs:photo_max":362,
    "qs:photo_sum":1766,
    "qs:placetype":"Suburb",
    "qs:quad_count":63,
    "qs:woe_adm0":23424945,
    "qs:woe_adm1":55848364,
    "qs:woe_adm2":12591568,
    "qs:woe_lau":0,
    "qs:woe_local":530634,
    "qs:woe_ver":"7.10.0",
    "wd:wordcount":336,
    "wof:lang":[
        "unk"
    ],
    "wof:name":"Be\u017eigrad",
    "wof:placetype":"neighbourhood"
},
  "geometry": {"coordinates":[14.513827,46.071225],"type":"Point"}
}