{
  "type": "Feature",
  "properties": {
    "gn:admin1_code":"13",
    "gn:asciiname":"Los Mendez",
    "gn:country_code":"SV",
    "gn:dem":71,
    "gn:feature_class":"P",
    "gn:feature_code":"PPL",
    "gn:name":"Los M\u00e9ndez",
    "gn:population":0,
    "gn:timezone":"America/El_Salvador",
    "iso:country":"SV",
    "wof:name":"Los Mendez",
    "wof:placetype":"locality"
},
  "geometry": {"coordinates":[-89.88333,13.68333],"type":"Point"}
}