{
  "type": "Feature",
  "properties": {
    "iso:country":"SV",
    "name:unk_x_variant":[
        "Cant\u00f3n Las Cruces"
    ],
    "qs:gn_country":"SV",
    "qs:gn_fcode":"PPL",
    "qs:gn_pop":0,
    "qs:name":"Las Cruces",
    "qs:name_adm0":"El Salvador",
    "qs:name_adm1":"Santa Ana",
    "qs:photos":36,
    "qs:photos_1k":7,
    "qs:photos_9k":1,
    "qs:photos_9r":2,
    "qs:photos_all":36,
    "qs:photos_sr":2,
    "qs:placetype":"Town",
    "qs:pop_sr":"0",
    "qs:woe_adm0":23424807,
    "wd:wordcount":81,
    "wof:name":"Las Cruces",
    "wof:placetype":"locality"
},
  "geometry": {"coordinates":[-89.65582999999999,13.91389],"type":"Point"}
}