{
  "type": "Feature",
  "properties": {
    "gn:admin1_code":"05",
    "gn:asciiname":"El Papaturral",
    "gn:cc2":"SV",
    "gn:country_code":"SV",
    "gn:dem":275,
    "gn:feature_class":"P",
    "gn:feature_code":"PPL",
    "gn:name":"El Papaturral",
    "gn:population":0,
    "gn:timezone":"America/El_Salvador",
    "iso:country":"SV",
    "name:und_x_variant":[
        "Sitio El Tablazo",
        "El Tablazo",
        "Sitio el Tablaso",
        "El Papaturral"
    ],
    "wof:name":"El Papaturral",
    "wof:placetype":"locality"
},
  "geometry": {"coordinates":[-89.31667,14.05],"type":"Point"}
}