{
  "type": "Feature",
  "properties": {
    "gn:admin1_code":"04",
    "gn:asciiname":"Los Naranjos",
    "gn:country_code":"SV",
    "gn:dem":807,
    "gn:feature_class":"P",
    "gn:feature_code":"PPL",
    "gn:name":"Los Naranjos",
    "gn:population":0,
    "gn:timezone":"America/El_Salvador",
    "iso:country":"SV",
    "wof:name":"Los Naranjos",
    "wof:placetype":"locality"
},
  "geometry": {"coordinates":[-88.91667,13.71667],"type":"Point"}
}