{
  "type": "Feature",
  "properties": {
    "gn:admin1_code":"04",
    "gn:asciiname":"El Centro",
    "gn:country_code":"SV",
    "gn:dem":721,
    "gn:feature_class":"P",
    "gn:feature_code":"PPL",
    "gn:name":"El Centro",
    "gn:population":0,
    "gn:timezone":"America/El_Salvador",
    "iso:country":"SV",
    "wof:name":"El Centro",
    "wof:placetype":"locality"
},
  "geometry": {"coordinates":[-88.96666999999999,13.73333],"type":"Point"}
}