{
  "type": "Feature",
  "properties": {
    "gn:admin1_code":"13",
    "gn:asciiname":"Tres Ceibas",
    "gn:cc2":"SV",
    "gn:country_code":"SV",
    "gn:dem":501,
    "gn:feature_class":"P",
    "gn:feature_code":"PPL",
    "gn:name":"Tres Ceibas",
    "gn:population":0,
    "gn:timezone":"America/El_Salvador",
    "iso:country":"SV",
    "name:und_x_variant":[
        "Las Tres Ceibas",
        "Tres Ceibas"
    ],
    "wof:name":"Tres Ceibas",
    "wof:placetype":"locality"
},
  "geometry": {"coordinates":[-89.47750000000001,13.75222],"type":"Point"}
}