{
  "type": "Feature",
  "properties": {
    "gn:admin1_code":"09",
    "gn:asciiname":"Primavera",
    "gn:country_code":"SV",
    "gn:dem":115,
    "gn:feature_class":"P",
    "gn:feature_code":"PPL",
    "gn:name":"Primavera",
    "gn:population":0,
    "gn:timezone":"America/El_Salvador",
    "iso:country":"SV",
    "wof:name":"Primavera",
    "wof:placetype":"locality"
},
  "geometry": {"coordinates":[-88.33333,13.35],"type":"Point"}
}