{
  "type": "Feature",
  "properties": {
    "gn:admin1_code":"04",
    "gn:asciiname":"Soledad",
    "gn:cc2":"SV",
    "gn:country_code":"SV",
    "gn:dem":761,
    "gn:feature_class":"P",
    "gn:feature_code":"PPL",
    "gn:name":"Soledad",
    "gn:population":0,
    "gn:timezone":"America/El_Salvador",
    "iso:country":"SV",
    "name:und_x_variant":[
        "La Soledad",
        "Soledad"
    ],
    "wof:name":"Soledad",
    "wof:placetype":"locality"
},
  "geometry": {"coordinates":[-88.88333,13.76667],"type":"Point"}
}