{
  "type": "Feature",
  "properties": {
    "gn:admin1_code":"04",
    "gn:asciiname":"Soledad",
    "gn:cc2":"SV",
    "gn:country_code":"SV",
    "gn:dem":761,
    "gn:feature_class":"P",
    "gn:feature_code":"PPL",
    "gn:name":"Soledad",
    "gn:population":0,
    "gn:timezone":"America/El_Salvador",
    "iso:country":"SV",
    "name:bre_x_preferred":[
        "Soledad"
    ],
    "name:cat_x_preferred":[
        "Soledad"
    ],
    "name:ceb_x_preferred":[
        "Soledad"
    ],
    "name:deu_x_preferred":[
        "Soledad"
    ],
    "name:fra_x_preferred":[
        "Soledad"
    ],
    "name:ita_x_preferred":[
        "Soledad"
    ],
    "name:lit_x_preferred":[
        "Soledad"
    ],
    "name:nld_x_preferred":[
        "Soledad"
    ],
    "name:pol_x_preferred":[
        "Soledad"
    ],
    "name:por_x_preferred":[
        "Soledad"
    ],
    "name:spa_x_preferred":[
        "Soledad"
    ],
    "name:srp_x_preferred":[
        "\u0421\u043e\u043b\u0435\u0434\u0430\u0434"
    ],
    "name:swe_x_preferred":[
        "Soledad"
    ],
    "name:und_x_variant":[
        "La Soledad",
        "Soledad"
    ],
    "name:vol_x_preferred":[
        "Soledad"
    ],
    "name:war_x_preferred":[
        "Soledad"
    ],
    "wof:name":"Soledad",
    "wof:placetype":"locality"
},
  "geometry": {"coordinates":[-88.88333,13.76667],"type":"Point"}
}