{
  "type": "Feature",
  "properties": {
    "gn:admin1_code":"11",
    "gn:asciiname":"La Virgen",
    "gn:country_code":"SV",
    "gn:dem":495,
    "gn:feature_class":"P",
    "gn:feature_code":"PPL",
    "gn:name":"La Virgen",
    "gn:population":0,
    "gn:timezone":"America/El_Salvador",
    "iso:country":"SV",
    "wof:name":"La Virgen",
    "wof:placetype":"locality"
},
  "geometry": {"coordinates":[-89.58333,14.35],"type":"Point"}
}