{
  "type": "Feature",
  "properties": {
    "gn:admin1_code":"04",
    "gn:asciiname":"Copapayo",
    "gn:cc2":"SV",
    "gn:country_code":"SV",
    "gn:dem":258,
    "gn:feature_class":"P",
    "gn:feature_code":"PPL",
    "gn:name":"Copapayo",
    "gn:population":0,
    "gn:timezone":"America/El_Salvador",
    "iso:country":"SV",
    "name:und_x_variant":[
        "Hacienda Copapayo",
        "Copapayo"
    ],
    "wof:name":"Copapayo",
    "wof:placetype":"locality"
},
  "geometry": {"coordinates":[-88.96666999999999,13.93333],"type":"Point"}
}