{
  "type": "Feature",
  "properties": {
    "gn:admin1_code":"14",
    "gn:asciiname":"Hacienda La Chepona",
    "gn:cc2":"SV",
    "gn:country_code":"SV",
    "gn:dem":4,
    "gn:feature_class":"P",
    "gn:feature_code":"PPL",
    "gn:name":"Hacienda La Chepona",
    "gn:population":0,
    "gn:timezone":"America/El_Salvador",
    "iso:country":"SV",
    "name:und_x_variant":[
        "La Chepona",
        "Hacienda Chepona",
        "Hacienda La Chepona"
    ],
    "wof:name":"Hacienda La Chepona",
    "wof:placetype":"locality"
},
  "geometry": {"coordinates":[-88.34999999999999,13.18333],"type":"Point"}
}