{
  "type": "Feature",
  "properties": {
    "gn:admin1_code":"10",
    "gn:asciiname":"El Zapote",
    "gn:country_code":"SV",
    "gn:dem":720,
    "gn:feature_class":"P",
    "gn:feature_code":"PPL",
    "gn:name":"El Zapote",
    "gn:population":0,
    "gn:timezone":"America/El_Salvador",
    "iso:country":"SV",
    "wof:name":"El Zapote",
    "wof:placetype":"locality"
},
  "geometry": {"coordinates":[-89.21666999999999,13.75],"type":"Point"}
}