{
  "type": "Feature",
  "properties": {
    "gn:admin1_code":"11",
    "gn:asciiname":"Los Planes de La Laguna",
    "gn:cc2":"SV",
    "gn:country_code":"SV",
    "gn:dem":986,
    "gn:feature_class":"P",
    "gn:feature_code":"PPL",
    "gn:name":"Los Planes de La Laguna",
    "gn:population":0,
    "gn:timezone":"America/El_Salvador",
    "iso:country":"SV",
    "name:und_x_variant":[
        "Planes de La Laguna",
        "Los Planes de La Laguna"
    ],
    "wof:name":"Los Planes de La Laguna",
    "wof:placetype":"locality"
},
  "geometry": {"coordinates":[-89.58750000000001,13.86333],"type":"Point"}
}