{
  "type": "Feature",
  "properties": {
    "gn:admin1_code":"12",
    "gn:asciiname":"San Pablo Canales",
    "gn:country_code":"SV",
    "gn:dem":392,
    "gn:feature_class":"P",
    "gn:feature_code":"PPL",
    "gn:name":"San Pablo Ca\u00f1ales",
    "gn:population":0,
    "gn:timezone":"America/El_Salvador",
    "iso:country":"SV",
    "wof:name":"San Pablo Canales",
    "wof:placetype":"locality"
},
  "geometry": {"coordinates":[-88.59999999999999,13.66667],"type":"Point"}
}