{
  "type": "Feature",
  "properties": {
    "gn:admin1_code":"08",
    "gn:asciiname":"Masala",
    "gn:country_code":"SV",
    "gn:dem":708,
    "gn:feature_class":"P",
    "gn:feature_code":"PPL",
    "gn:name":"Masala",
    "gn:population":0,
    "gn:timezone":"America/El_Salvador",
    "iso:country":"SV",
    "name:ceb_x_preferred":[
        "Masala"
    ],
    "name:deu_x_preferred":[
        "Masala"
    ],
    "name:fra_x_preferred":[
        "Masala"
    ],
    "name:heb_x_preferred":[
        "\u05de\u05e1\u05d0\u05dc\u05d4"
    ],
    "name:ita_x_preferred":[
        "Masala"
    ],
    "name:pol_x_preferred":[
        "Masala"
    ],
    "name:rus_x_preferred":[
        "\u041c\u0430\u0441\u0430\u043b\u0430"
    ],
    "name:swe_x_preferred":[
        "Masala"
    ],
    "wof:name":"Masala",
    "wof:placetype":"locality"
},
  "geometry": {"coordinates":[-88.08333,13.91667],"type":"Point"}
}