{
  "type": "Feature",
  "properties": {
    "gn:admin1_code":"05",
    "gn:asciiname":"La Montanita",
    "gn:country_code":"SV",
    "gn:dem":556,
    "gn:feature_class":"P",
    "gn:feature_code":"PPL",
    "gn:name":"La Monta\u00f1ita",
    "gn:population":0,
    "gn:timezone":"America/El_Salvador",
    "iso:country":"SV",
    "wof:name":"La Montanita",
    "wof:placetype":"locality"
},
  "geometry": {"coordinates":[-89.45,13.73333],"type":"Point"}
}