{
  "type": "Feature",
  "properties": {
    "gn:admin1_code":"14",
    "gn:asciiname":"Roquinte",
    "gn:cc2":"SV",
    "gn:country_code":"SV",
    "gn:dem":34,
    "gn:feature_class":"P",
    "gn:feature_code":"PPL",
    "gn:name":"Roquinte",
    "gn:population":0,
    "gn:timezone":"America/El_Salvador",
    "iso:country":"SV",
    "name:und_x_variant":[
        "El Roquinte",
        "Roquinte"
    ],
    "wof:name":"Roquinte",
    "wof:placetype":"locality"
},
  "geometry": {"coordinates":[-88.56667,13.31667],"type":"Point"}
}