{
  "type": "Feature",
  "properties": {
    "iso:country":"SV",
    "name:bul_x_preferred":[
        "\u0410\u044e\u0442\u0443\u0441\u0442\u0435\u043f\u0435\u043a\u0435"
    ],
    "name:chi_x_preferred":[
        "\u963f\u5c24\u5716\u65af\u7279\u4f69\u514b"
    ],
    "name:deu_x_preferred":[
        "Ayutuxtepeque"
    ],
    "name:dut_x_preferred":[
        "Ayutuxtepeque"
    ],
    "name:eng_x_preferred":[
        "Ayutuxtepeque"
    ],
    "name:fre_x_preferred":[
        "Ayutuxtepeque"
    ],
    "name:ger_x_preferred":[
        "Ayutuxtepeque"
    ],
    "name:ita_x_preferred":[
        "Ayutuxtepeque"
    ],
    "name:jpn_x_preferred":[
        "\u30a2\u30e6\u30c8\u30a5\u30b9\u30c6\u30da\u30b1"
    ],
    "name:nah_x_preferred":[
        "\u0100y\u014dt\u014dchtep\u0113c"
    ],
    "name:pol_x_preferred":[
        "Ayutuxtepeque"
    ],
    "name:por_x_preferred":[
        "Ayutuxtepeque"
    ],
    "name:spa_x_preferred":[
        "Ayutuxtepeque"
    ],
    "name:unk_x_variant":[
        "Ayutuxtepegue"
    ],
    "name:zho_x_preferred":[
        "\u963f\u5c24\u5716\u65af\u7279\u4f69\u514b"
    ],
    "qs:gn_country":"SV",
    "qs:gn_fcode":"PPL",
    "qs:gn_pop":25426,
    "qs:name":"Ayutuxtepeque",
    "qs:name_adm0":"El Salvador",
    "qs:name_adm1":"San Salvador",
    "qs:photos":207,
    "qs:photos_1k":42,
    "qs:photos_9k":1,
    "qs:photos_9r":4,
    "qs:photos_all":207,
    "qs:photos_sr":4,
    "qs:placetype":"Town",
    "qs:pop_sr":"7",
    "qs:woe_adm0":23424807,
    "wof:name":"Ayutuxtepeque",
    "wof:placetype":"locality",
    "wof:population":25426
},
  "geometry": {"coordinates":[-89.20639,13.74556],"type":"Point"}
}