{
  "type": "Feature",
  "properties": {
    "gn:admin1_code":"05",
    "gn:asciiname":"Chiltiupan",
    "gn:country_code":"SV",
    "gn:dem":691,
    "gn:feature_class":"P",
    "gn:feature_code":"PPL",
    "gn:name":"Chiltiup\u00e1n",
    "gn:population":0,
    "gn:timezone":"America/El_Salvador",
    "iso:country":"SV",
    "name:ceb_x_preferred":[
        "Chiltiup\u00e1n"
    ],
    "name:ita_x_preferred":[
        "Chiltiup\u00e1n"
    ],
    "name:por_x_preferred":[
        "Chiltiup\u00e1n"
    ],
    "name:spa_x_preferred":[
        "Chiltiup\u00e1n"
    ],
    "name:und_x_variant":[
        "Chiltiup\u00e1n"
    ],
    "name:zho_x_preferred":[
        "\u5947\u723e\u8482\u70cf\u6f58"
    ],
    "wof:name":"Chiltiupan",
    "wof:placetype":"locality"
},
  "geometry": {"coordinates":[-89.46889,13.59056],"type":"Point"}
}