{
  "type": "Feature",
  "properties": {
    "gn:admin1_code":"08",
    "gn:asciiname":"La Loma",
    "gn:country_code":"SV",
    "gn:dem":432,
    "gn:feature_class":"P",
    "gn:feature_code":"PPL",
    "gn:name":"La Loma",
    "gn:population":0,
    "gn:timezone":"America/El_Salvador",
    "iso:country":"SV",
    "wof:name":"La Loma",
    "wof:placetype":"locality"
},
  "geometry": {"coordinates":[-88.16667,13.83333],"type":"Point"}
}