{
  "type": "Feature",
  "properties": {
    "gn:admin1_code":"13",
    "gn:asciiname":"La Puente",
    "gn:country_code":"SV",
    "gn:dem":1301,
    "gn:feature_class":"P",
    "gn:feature_code":"PPL",
    "gn:name":"La Puente",
    "gn:population":0,
    "gn:timezone":"America/El_Salvador",
    "iso:country":"SV",
    "wof:name":"La Puente",
    "wof:placetype":"locality"
},
  "geometry": {"coordinates":[-89.75,13.88333],"type":"Point"}
}