{
  "type": "Feature",
  "properties": {
    "gn:admin1_code":"09",
    "gn:asciiname":"Chilamate",
    "gn:cc2":"SV",
    "gn:country_code":"SV",
    "gn:dem":294,
    "gn:feature_class":"P",
    "gn:feature_code":"PPL",
    "gn:name":"Chilamate",
    "gn:population":0,
    "gn:timezone":"America/El_Salvador",
    "iso:country":"SV",
    "name:und_x_variant":[
        "El Chilamate",
        "Chilamate"
    ],
    "wof:name":"Chilamate",
    "wof:placetype":"locality"
},
  "geometry": {"coordinates":[-88.40000000000001,13.68333],"type":"Point"}
}