{
  "type": "Feature",
  "properties": {
    "gn:admin1_code":"01",
    "gn:asciiname":"Hacienda El Chaguite",
    "gn:cc2":"SV",
    "gn:country_code":"SV",
    "gn:dem":148,
    "gn:feature_class":"P",
    "gn:feature_code":"PPL",
    "gn:name":"Hacienda El Chag\u00fcite",
    "gn:population":0,
    "gn:timezone":"America/El_Salvador",
    "iso:country":"SV",
    "name:und_x_variant":[
        "El Chaguite",
        "Hacienda El Chag\u00fcite"
    ],
    "wof:name":"Hacienda El Chaguite",
    "wof:placetype":"locality"
},
  "geometry": {"coordinates":[-89.90000000000001,13.73333],"type":"Point"}
}