{
  "type": "Feature",
  "properties": {
    "gn:admin1_code":"12",
    "gn:asciiname":"Sanqueque",
    "gn:cc2":"SV",
    "gn:country_code":"SV",
    "gn:dem":238,
    "gn:feature_class":"P",
    "gn:feature_code":"PPL",
    "gn:name":"Sanqueque",
    "gn:population":0,
    "gn:timezone":"America/El_Salvador",
    "iso:country":"SV",
    "name:und_x_variant":[
        "Caser\u00edo Sunquenque",
        "Sunquenque",
        "Sanqueque"
    ],
    "wof:name":"Sanqueque",
    "wof:placetype":"locality"
},
  "geometry": {"coordinates":[-88.68333,13.51667],"type":"Point"}
}