{
  "type": "Feature",
  "properties": {
    "gn:admin1_code":"11",
    "gn:asciiname":"Ochupse Abajo",
    "gn:country_code":"SV",
    "gn:dem":938,
    "gn:feature_class":"P",
    "gn:feature_code":"PPL",
    "gn:name":"Ochupse Abajo",
    "gn:population":0,
    "gn:timezone":"America/El_Salvador",
    "iso:country":"SV",
    "wof:name":"Ochupse Abajo",
    "wof:placetype":"locality"
},
  "geometry": {"coordinates":[-89.58528000000003,13.92167],"type":"Point"}
}