{
  "type": "Feature",
  "properties": {
    "gn:admin1_code":"03",
    "gn:asciiname":"Llano Verde",
    "gn:country_code":"SV",
    "gn:dem":394,
    "gn:feature_class":"P",
    "gn:feature_code":"PPL",
    "gn:name":"Llano Verde",
    "gn:population":0,
    "gn:timezone":"America/El_Salvador",
    "iso:country":"SV",
    "wof:name":"Llano Verde",
    "wof:placetype":"locality"
},
  "geometry": {"coordinates":[-88.83333,14.05],"type":"Point"}
}