{
  "type": "Feature",
  "properties": {
    "gn:admin1_code":"10",
    "gn:asciiname":"Nance Verde",
    "gn:cc2":"SV",
    "gn:country_code":"SV",
    "gn:dem":865,
    "gn:feature_class":"P",
    "gn:feature_code":"PPL",
    "gn:name":"Nance Verde",
    "gn:population":0,
    "gn:timezone":"America/El_Salvador",
    "iso:country":"SV",
    "name:und_x_variant":[
        "Cant\u00f3n Nance Verde",
        "Nance Verde"
    ],
    "wof:name":"Nance Verde",
    "wof:placetype":"locality"
},
  "geometry": {"coordinates":[-89.13333,13.88333],"type":"Point"}
}