{
  "type": "Feature",
  "properties": {
    "gn:admin1_code":"06",
    "gn:asciiname":"Santa Fe",
    "gn:country_code":"SV",
    "gn:dem":252,
    "gn:feature_class":"P",
    "gn:feature_code":"PPL",
    "gn:name":"Santa Fe",
    "gn:population":0,
    "gn:timezone":"America/El_Salvador",
    "iso:country":"SV",
    "wof:name":"Santa Fe",
    "wof:placetype":"locality"
},
  "geometry": {"coordinates":[-89.13333,13.51667],"type":"Point"}
}