{
  "type": "Feature",
  "properties": {
    "gn:admin1_code":"04",
    "gn:asciiname":"Copinol",
    "gn:cc2":"SV",
    "gn:country_code":"SV",
    "gn:dem":733,
    "gn:feature_class":"P",
    "gn:feature_code":"PPL",
    "gn:name":"Copinol",
    "gn:population":0,
    "gn:timezone":"America/El_Salvador",
    "iso:country":"SV",
    "name:und_x_variant":[
        "El Copinol",
        "Copinol"
    ],
    "wof:name":"Copinol",
    "wof:placetype":"locality"
},
  "geometry": {"coordinates":[-88.88333,13.75],"type":"Point"}
}