{
  "type": "Feature",
  "properties": {
    "gn:admin1_code":"09",
    "gn:asciiname":"La Quebradona",
    "gn:country_code":"SV",
    "gn:dem":322,
    "gn:feature_class":"P",
    "gn:feature_code":"PPL",
    "gn:name":"La Quebradona",
    "gn:population":0,
    "gn:timezone":"America/El_Salvador",
    "iso:country":"SV",
    "name:ceb_x_preferred":[
        "La Quebradona"
    ],
    "name:swe_x_preferred":[
        "La Quebradona"
    ],
    "wof:name":"La Quebradona",
    "wof:placetype":"locality"
},
  "geometry": {"coordinates":[-88.31667,13.83333],"type":"Point"}
}