{
  "type": "Feature",
  "properties": {
    "gn:admin1_code":"01",
    "gn:asciiname":"El Sincuyo",
    "gn:country_code":"SV",
    "gn:dem":778,
    "gn:feature_class":"P",
    "gn:feature_code":"PPL",
    "gn:name":"El Sincuyo",
    "gn:population":0,
    "gn:timezone":"America/El_Salvador",
    "iso:country":"SV",
    "wof:name":"El Sincuyo",
    "wof:placetype":"locality"
},
  "geometry": {"coordinates":[-89.94583,13.88222],"type":"Point"}
}