{
  "type": "Feature",
  "properties": {
    "gn:admin1_code":"11",
    "gn:asciiname":"La Gloria",
    "gn:cc2":"SV",
    "gn:country_code":"SV",
    "gn:dem":706,
    "gn:feature_class":"P",
    "gn:feature_code":"PPL",
    "gn:name":"La Gloria",
    "gn:population":0,
    "gn:timezone":"America/El_Salvador",
    "iso:country":"SV",
    "name:ast_x_preferred":[
        "La Gloria"
    ],
    "name:ceb_x_preferred":[
        "La Gloria"
    ],
    "name:deu_x_preferred":[
        "La Gloria"
    ],
    "name:ita_x_preferred":[
        "La Gloria"
    ],
    "name:nld_x_preferred":[
        "La Gloria"
    ],
    "name:spa_x_preferred":[
        "La Gloria"
    ],
    "name:swe_x_preferred":[
        "La Gloria"
    ],
    "name:und_x_variant":[
        "Caser\u00edo La Gloria"
    ],
    "name:vie_x_preferred":[
        "La Gloria"
    ],
    "wof:name":"La Gloria",
    "wof:placetype":"locality"
},
  "geometry": {"coordinates":[-89.51666999999998,13.95],"type":"Point"}
}