{
  "type": "Feature",
  "properties": {
    "gn:admin1_code":"12",
    "gn:asciiname":"Santa Gertrudis",
    "gn:country_code":"SV",
    "gn:dem":419,
    "gn:feature_class":"P",
    "gn:feature_code":"PPL",
    "gn:name":"Santa Gertrudis",
    "gn:population":0,
    "gn:timezone":"America/El_Salvador",
    "iso:country":"SV",
    "name:cat_x_preferred":[
        "Santa Gertrudis"
    ],
    "name:ceb_x_preferred":[
        "Santa Gertrudis"
    ],
    "name:deu_x_preferred":[
        "Santa Gertrudis"
    ],
    "name:sco_x_preferred":[
        "Santa Gertrudis"
    ],
    "name:spa_x_preferred":[
        "Santa Gertrudis"
    ],
    "name:swe_x_preferred":[
        "Santa Gertrudis"
    ],
    "wof:name":"Santa Gertrudis",
    "wof:placetype":"locality"
},
  "geometry": {"coordinates":[-88.76666999999998,13.58333],"type":"Point"}
}