{
  "type": "Feature",
  "properties": {
    "gn:admin1_code":"11",
    "gn:asciiname":"Plan de Las Marias",
    "gn:cc2":"SV",
    "gn:country_code":"SV",
    "gn:dem":1070,
    "gn:feature_class":"P",
    "gn:feature_code":"PPL",
    "gn:name":"Plan de Las Mar\u00edas",
    "gn:population":0,
    "gn:timezone":"America/El_Salvador",
    "iso:country":"SV",
    "name:und_x_variant":[
        "Las Mar\u00edas",
        "Caser\u00edo Las Mar\u00edas",
        "Plan de Las Mar\u00edas"
    ],
    "wof:name":"Plan de Las Marias",
    "wof:placetype":"locality"
},
  "geometry": {"coordinates":[-89.46722,13.91667],"type":"Point"}
}