{
  "type": "Feature",
  "properties": {
    "gn:admin1_code":"07",
    "gn:asciiname":"Los Picachos",
    "gn:country_code":"SV",
    "gn:dem":490,
    "gn:feature_class":"P",
    "gn:feature_code":"PPL",
    "gn:name":"Los Picachos",
    "gn:population":0,
    "gn:timezone":"America/El_Salvador",
    "iso:country":"SV",
    "wof:name":"Los Picachos",
    "wof:placetype":"locality"
},
  "geometry": {"coordinates":[-87.90000000000001,13.85],"type":"Point"}
}