{
  "type": "Feature",
  "properties": {
    "gn:admin1_code":"07",
    "gn:asciiname":"Canoguero",
    "gn:cc2":"SV",
    "gn:country_code":"SV",
    "gn:dem":22,
    "gn:feature_class":"P",
    "gn:feature_code":"PPL",
    "gn:name":"Canoguero",
    "gn:population":0,
    "gn:timezone":"America/El_Salvador",
    "iso:country":"SV",
    "name:und_x_variant":[
        "Conaguero",
        "Canoguero"
    ],
    "wof:name":"Canoguero",
    "wof:placetype":"locality"
},
  "geometry": {"coordinates":[-87.95,13.16667],"type":"Point"}
}