{
  "type": "Feature",
  "properties": {
    "gn:admin1_code":"08",
    "gn:asciiname":"La Calavera",
    "gn:cc2":"SV",
    "gn:country_code":"SV",
    "gn:dem":235,
    "gn:feature_class":"P",
    "gn:feature_code":"PPL",
    "gn:name":"La Calavera",
    "gn:population":0,
    "gn:timezone":"America/El_Salvador",
    "iso:country":"SV",
    "name:und_x_variant":[
        "Las Calavera",
        "Las Calaveras",
        "La Calavera"
    ],
    "wof:name":"La Calavera",
    "wof:placetype":"locality"
},
  "geometry": {"coordinates":[-87.98333000000002,13.63333],"type":"Point"}
}