{
  "type": "Feature",
  "properties": {
    "gn:admin1_code":"11",
    "gn:asciiname":"Las Higueras",
    "gn:country_code":"SV",
    "gn:dem":1699,
    "gn:feature_class":"P",
    "gn:feature_code":"PPL",
    "gn:name":"Las Higueras",
    "gn:population":0,
    "gn:timezone":"America/El_Salvador",
    "iso:country":"SV",
    "wof:name":"Las Higueras",
    "wof:placetype":"locality"
},
  "geometry": {"coordinates":[-89.31667,14.38333],"type":"Point"}
}