{
  "type": "Feature",
  "properties": {
    "gn:admin1_code":"11",
    "gn:asciiname":"Valle El Cerro",
    "gn:country_code":"SV",
    "gn:dem":554,
    "gn:feature_class":"P",
    "gn:feature_code":"PPL",
    "gn:name":"Valle El Cerro",
    "gn:population":0,
    "gn:timezone":"America/El_Salvador",
    "iso:country":"SV",
    "wof:name":"Valle El Cerro",
    "wof:placetype":"locality"
},
  "geometry": {"coordinates":[-89.30278,13.89194],"type":"Point"}
}