{
  "type": "Feature",
  "properties": {
    "gn:admin1_code":"13",
    "gn:asciiname":"El Amatal",
    "gn:cc2":"SV",
    "gn:country_code":"SV",
    "gn:dem":-9999,
    "gn:feature_class":"P",
    "gn:feature_code":"PPL",
    "gn:name":"El Amatal",
    "gn:population":0,
    "gn:timezone":"America/El_Salvador",
    "iso:country":"SV",
    "name:und_x_variant":[
        "Cant\u00f3n El Amatal",
        "El Amatal"
    ],
    "wof:name":"El Amatal",
    "wof:placetype":"locality"
},
  "geometry": {"coordinates":[-89.90000000000001,13.63333],"type":"Point"}
}