{
  "type": "Feature",
  "properties": {
    "gn:admin1_code":"11",
    "gn:asciiname":"San Antonio Masahuat",
    "gn:country_code":"SV",
    "gn:dem":636,
    "gn:feature_class":"P",
    "gn:feature_code":"PPL",
    "gn:name":"San Antonio Masahuat",
    "gn:population":0,
    "gn:timezone":"America/El_Salvador",
    "iso:country":"SV",
    "name:ceb_x_preferred":[
        "San Antonio Masahuat"
    ],
    "name:fra_x_preferred":[
        "San Antonio Masahuat"
    ],
    "name:ita_x_preferred":[
        "San Antonio Masahuat"
    ],
    "name:por_x_preferred":[
        "San Antonio Masahuat"
    ],
    "name:spa_x_preferred":[
        "San Antonio Masahuat"
    ],
    "name:zho_x_preferred":[
        "\u8056\u5b89\u6771\u5c3c\u5967\u99ac\u85a9\u74e6\u7279"
    ],
    "wof:name":"San Antonio Masahuat",
    "wof:placetype":"locality"
},
  "geometry": {"coordinates":[-89.46666999999999,14.16667],"type":"Point"}
}