{
  "type": "Feature",
  "properties": {
    "gn:admin1_code":"11",
    "gn:asciiname":"San Antonio Masahuat",
    "gn:country_code":"SV",
    "gn:dem":636,
    "gn:feature_class":"P",
    "gn:feature_code":"PPL",
    "gn:name":"San Antonio Masahuat",
    "gn:population":0,
    "gn:timezone":"America/El_Salvador",
    "iso:country":"SV",
    "wof:name":"San Antonio Masahuat",
    "wof:placetype":"locality"
},
  "geometry": {"coordinates":[-89.46666999999999,14.16667],"type":"Point"}
}