{
  "type": "Feature",
  "properties": {
    "gn:admin1_code":"03",
    "gn:asciiname":"Las Pilas",
    "gn:country_code":"SV",
    "gn:dem":1969,
    "gn:feature_class":"P",
    "gn:feature_code":"PPL",
    "gn:name":"Las Pilas",
    "gn:population":0,
    "gn:timezone":"America/El_Salvador",
    "iso:country":"SV",
    "name:fra_x_preferred":[
        "Las Pilas"
    ],
    "name:lit_x_preferred":[
        "Las Pilasas"
    ],
    "name:nld_x_preferred":[
        "Las Pilas"
    ],
    "name:rus_x_preferred":[
        "\u041b\u0430\u0441-\u041f\u0438\u043b\u0430\u0441"
    ],
    "name:slk_x_preferred":[
        "Las Pilas"
    ],
    "wof:name":"Las Pilas",
    "wof:placetype":"locality"
},
  "geometry": {"coordinates":[-89.09999999999999,14.36667],"type":"Point"}
}