{
  "type": "Feature",
  "properties": {
    "gn:admin1_code":"11",
    "gn:asciiname":"Las Dos Hojas",
    "gn:country_code":"SV",
    "gn:dem":372,
    "gn:feature_class":"P",
    "gn:feature_code":"PPL",
    "gn:name":"Las Dos Hojas",
    "gn:population":0,
    "gn:timezone":"America/El_Salvador",
    "iso:country":"SV",
    "wof:name":"Las Dos Hojas",
    "wof:placetype":"locality"
},
  "geometry": {"coordinates":[-89.29722,13.91028],"type":"Point"}
}