{
  "type": "Feature",
  "properties": {
    "gn:admin1_code":"09",
    "gn:asciiname":"Las Barrancas",
    "gn:cc2":"SV",
    "gn:country_code":"SV",
    "gn:dem":264,
    "gn:feature_class":"P",
    "gn:feature_code":"PPL",
    "gn:name":"Las Barrancas",
    "gn:population":0,
    "gn:timezone":"America/El_Salvador",
    "iso:country":"SV",
    "name:und_x_variant":[
        "Barranca",
        "Las Barrancas"
    ],
    "wof:name":"Las Barrancas",
    "wof:placetype":"locality"
},
  "geometry": {"coordinates":[-88.48333000000002,13.78333],"type":"Point"}
}