{
  "type": "Feature",
  "properties": {
    "gn:admin1_code":"07",
    "gn:asciiname":"La Rinconada",
    "gn:country_code":"SV",
    "gn:dem":115,
    "gn:feature_class":"P",
    "gn:feature_code":"PPL",
    "gn:name":"La Rinconada",
    "gn:population":0,
    "gn:timezone":"America/El_Salvador",
    "iso:country":"SV",
    "wof:name":"La Rinconada",
    "wof:placetype":"locality"
},
  "geometry": {"coordinates":[-87.93722,13.54],"type":"Point"}
}