{
  "type": "Feature",
  "properties": {
    "gn:admin1_code":"05",
    "gn:asciiname":"Amaquilco",
    "gn:country_code":"SV",
    "gn:dem":621,
    "gn:feature_class":"P",
    "gn:feature_code":"PPL",
    "gn:name":"Amaquilco",
    "gn:population":0,
    "gn:timezone":"America/El_Salvador",
    "iso:country":"SV",
    "wof:name":"Amaquilco",
    "wof:placetype":"locality"
},
  "geometry": {"coordinates":[-89.25,13.58333],"type":"Point"}
}