{
  "type": "Feature",
  "properties": {
    "gn:admin1_code":"01",
    "gn:asciiname":"El Escalon",
    "gn:country_code":"SV",
    "gn:dem":267,
    "gn:feature_class":"P",
    "gn:feature_code":"PPL",
    "gn:name":"El Escal\u00f3n",
    "gn:population":0,
    "gn:timezone":"America/El_Salvador",
    "iso:country":"SV",
    "wof:name":"El Escalon",
    "wof:placetype":"locality"
},
  "geometry": {"coordinates":[-89.83333,13.73333],"type":"Point"}
}