{
  "type": "Feature",
  "properties": {
    "gn:admin1_code":"10",
    "gn:asciiname":"Malacof",
    "gn:cc2":"SV",
    "gn:country_code":"SV",
    "gn:dem":689,
    "gn:feature_class":"P",
    "gn:feature_code":"PPL",
    "gn:name":"Malacof",
    "gn:population":0,
    "gn:timezone":"America/El_Salvador",
    "iso:country":"SV",
    "name:und_x_variant":[
        "Malacoff",
        "Malacof"
    ],
    "wof:name":"Malacof",
    "wof:placetype":"locality"
},
  "geometry": {"coordinates":[-89.10056,13.76444],"type":"Point"}
}