{
  "type": "Feature",
  "properties": {
    "gn:admin1_code":"05",
    "gn:asciiname":"Chanmico",
    "gn:country_code":"SV",
    "gn:dem":469,
    "gn:feature_class":"P",
    "gn:feature_code":"PPL",
    "gn:name":"Chanmico",
    "gn:population":0,
    "gn:timezone":"America/El_Salvador",
    "iso:country":"SV",
    "wof:name":"Chanmico",
    "wof:placetype":"locality"
},
  "geometry": {"coordinates":[-89.35639,13.78722],"type":"Point"}
}