{
  "type": "Feature",
  "properties": {
    "gn:admin1_code":"07",
    "gn:asciiname":"El Borbollon",
    "gn:country_code":"SV",
    "gn:dem":73,
    "gn:feature_class":"P",
    "gn:feature_code":"PPL",
    "gn:name":"El Borboll\u00f3n",
    "gn:population":0,
    "gn:timezone":"America/El_Salvador",
    "iso:country":"SV",
    "wof:name":"El Borbollon",
    "wof:placetype":"locality"
},
  "geometry": {"coordinates":[-88.03083000000002,13.29361],"type":"Point"}
}