{
  "type": "Feature",
  "properties": {
    "gn:admin1_code":"11",
    "gn:asciiname":"Valle Campana",
    "gn:cc2":"SV",
    "gn:country_code":"SV",
    "gn:dem":1881,
    "gn:feature_class":"P",
    "gn:feature_code":"PPL",
    "gn:name":"Valle Campana",
    "gn:population":0,
    "gn:timezone":"America/El_Salvador",
    "iso:country":"SV",
    "name:und_x_variant":[
        "Campana",
        "Valle Campana"
    ],
    "wof:name":"Valle Campana",
    "wof:placetype":"locality"
},
  "geometry": {"coordinates":[-89.61667,13.85],"type":"Point"}
}