{
  "type": "Feature",
  "properties": {
    "gn:country":"SV",
    "gn:fcode":"PPLX",
    "gn:population":0,
    "iso:country":"SV",
    "name:spa_x_preferred":[
        "Colonia San Benito"
    ],
    "name:spa_x_variant":[
        "Colonia S. Benito",
        "Colonia S Benito",
        "S. Benito",
        "S Benito",
        "San Benito"
    ],
    "qs:gn_adm0_cc":"SV",
    "qs:gn_fcode":"PPLX",
    "qs:gn_local":3583361,
    "qs:gn_nam_loc":"San Salvador, San Salvador, San Salvador, SV",
    "qs:gn_namadm1":"10",
    "qs:gn_name":"Colonia San Benito",
    "qs:local_max":3481,
    "qs:local_sum":9209,
    "qs:localhoods":7,
    "qs:name":"Colonia San Benito",
    "qs:name_adm0":"El Salvador",
    "qs:name_adm1":"San Salvador",
    "qs:name_adm2":"San Salvador",
    "qs:name_local":"San Salvador",
    "qs:photo_max":572,
    "qs:photo_sum":1266,
    "qs:placetype":"Suburb",
    "qs:quad_count":53,
    "qs:woe_adm0":23424807,
    "qs:woe_adm1":2345301,
    "qs:woe_adm2":26808700,
    "qs:woe_lau":0,
    "qs:woe_local":79825,
    "qs:woe_ver":"7.10.0",
    "qs_pg:aaroncc":"SV",
    "qs_pg:gn_country":"SV",
    "qs_pg:gn_fcode":"PPLX",
    "qs_pg:gn_pop":0,
    "qs_pg:name":"Colonia San Benito",
    "qs_pg:name_adm0":"El Salvador",
    "qs_pg:name_adm1":"San Salvador",
    "qs_pg:photos":1132,
    "qs_pg:photos_1k":229,
    "qs_pg:photos_9k":5,
    "qs_pg:photos_9r":7,
    "qs_pg:photos_all":1132,
    "qs_pg:photos_sr":11,
    "qs_pg:pop_sr":0,
    "qs_pg:qs_pg_placetype":"neighbourhood",
    "qs_pg:qs_pg_placetype_gp":"Suburb",
    "qs_pg:woe_adm0":23424807,
    "wof:lang":[
        "spa"
    ],
    "wof:name":"Colonia San Benito",
    "wof:placetype":"neighbourhood"
},
  "geometry": {"coordinates":[-89.24530900000001,13.692971],"type":"Point"}
}