{
  "type": "Feature",
  "properties": {
    "gn:admin1_code":"03",
    "gn:asciiname":"El Transito",
    "gn:country_code":"SV",
    "gn:dem":435,
    "gn:feature_class":"P",
    "gn:feature_code":"PPL",
    "gn:name":"El Tr\u00e1nsito",
    "gn:population":0,
    "gn:timezone":"America/El_Salvador",
    "iso:country":"SV",
    "wof:name":"El Transito",
    "wof:placetype":"locality"
},
  "geometry": {"coordinates":[-89.09999999999999,14.15],"type":"Point"}
}