{
  "type": "Feature",
  "properties": {
    "gn:admin1_code":"10",
    "gn:asciiname":"Changallo",
    "gn:country_code":"SV",
    "gn:dem":482,
    "gn:feature_class":"P",
    "gn:feature_code":"PPL",
    "gn:name":"Changallo",
    "gn:population":0,
    "gn:timezone":"America/El_Salvador",
    "iso:country":"SV",
    "wof:name":"Changallo",
    "wof:placetype":"locality"
},
  "geometry": {"coordinates":[-89.11778000000002,13.66917],"type":"Point"}
}