{
  "type": "Feature",
  "properties": {
    "gn:admin1_code":"10",
    "gn:asciiname":"El Callejon",
    "gn:cc2":"SV",
    "gn:country_code":"SV",
    "gn:dem":670,
    "gn:feature_class":"P",
    "gn:feature_code":"PPL",
    "gn:name":"El Callej\u00f3n",
    "gn:population":0,
    "gn:timezone":"America/El_Salvador",
    "iso:country":"SV",
    "name:und_x_variant":[
        "Callejon",
        "El Callej\u00f3n"
    ],
    "wof:name":"El Callejon",
    "wof:placetype":"locality"
},
  "geometry": {"coordinates":[-89.18333,13.75],"type":"Point"}
}