{
  "type": "Feature",
  "properties": {
    "gn:admin1_code":"10",
    "gn:asciiname":"Venecia",
    "gn:cc2":"SV",
    "gn:country_code":"SV",
    "gn:dem":649,
    "gn:feature_class":"P",
    "gn:feature_code":"PPL",
    "gn:name":"Venecia",
    "gn:population":0,
    "gn:timezone":"America/El_Salvador",
    "iso:country":"SV",
    "name:ceb_x_preferred":[
        "Venecia"
    ],
    "name:ita_x_preferred":[
        "Venecia"
    ],
    "name:msa_x_preferred":[
        "Venecia"
    ],
    "name:nld_x_preferred":[
        "Venecia"
    ],
    "name:spa_x_preferred":[
        "Venecia"
    ],
    "name:srp_x_preferred":[
        "\u0412\u0435\u043d\u0435\u0441\u0438\u0458\u0430"
    ],
    "name:swe_x_preferred":[
        "Venecia"
    ],
    "name:und_x_variant":[
        "Finca Venecia"
    ],
    "name:war_x_preferred":[
        "Venecia"
    ],
    "wof:name":"Venecia",
    "wof:placetype":"locality"
},
  "geometry": {"coordinates":[-89.15000000000001,13.71667],"type":"Point"}
}