{
  "type": "Feature",
  "properties": {
    "gn:admin1_code":"03",
    "gn:asciiname":"Valle Nuevo",
    "gn:country_code":"SV",
    "gn:dem":295,
    "gn:feature_class":"P",
    "gn:feature_code":"PPL",
    "gn:name":"Valle Nuevo",
    "gn:population":0,
    "gn:timezone":"America/El_Salvador",
    "iso:country":"SV",
    "wof:name":"Valle Nuevo",
    "wof:placetype":"locality"
},
  "geometry": {"coordinates":[-89.08333,14.11667],"type":"Point"}
}