{
  "type": "Feature",
  "properties": {
    "gn:admin1_code":"13",
    "gn:asciiname":"Pushtan",
    "gn:cc2":"SV",
    "gn:country_code":"SV",
    "gn:dem":494,
    "gn:feature_class":"P",
    "gn:feature_code":"PPL",
    "gn:name":"Pusht\u00e1n",
    "gn:population":0,
    "gn:timezone":"America/El_Salvador",
    "iso:country":"SV",
    "name:und_x_variant":[
        "Pucht\u00e1n",
        "Pusht\u00e1n"
    ],
    "wof:name":"Pushtan",
    "wof:placetype":"locality"
},
  "geometry": {"coordinates":[-89.72,13.76722],"type":"Point"}
}