{
  "type": "Feature",
  "properties": {
    "gn:admin1_code":"10",
    "gn:asciiname":"Guapa",
    "gn:cc2":"SV",
    "gn:country_code":"SV",
    "gn:dem":743,
    "gn:feature_class":"P",
    "gn:feature_code":"PPL",
    "gn:name":"Guapa",
    "gn:population":0,
    "gn:timezone":"America/El_Salvador",
    "iso:country":"SV",
    "name:fra_x_preferred":[
        "Guapa"
    ],
    "name:spa_x_preferred":[
        "Guapa"
    ],
    "name:und_x_variant":[
        "Cuapa"
    ],
    "wof:name":"Guapa",
    "wof:placetype":"locality"
},
  "geometry": {"coordinates":[-89.14667,13.66667],"type":"Point"}
}