{
  "type": "Feature",
  "properties": {
    "gn:admin1_code":"02",
    "gn:asciiname":"Guiliguiste",
    "gn:cc2":"SV",
    "gn:country_code":"SV",
    "gn:dem":485,
    "gn:feature_class":"P",
    "gn:feature_code":"PPL",
    "gn:name":"G\u00fcilig\u00fciste",
    "gn:population":0,
    "gn:timezone":"America/El_Salvador",
    "iso:country":"SV",
    "name:und_x_variant":[
        "El G\u00fcilig\u00fciste",
        "El Guilihuiste",
        "G\u00fcilih\u00fciste",
        "Huilihuiste",
        "G\u00fcilig\u00fciste"
    ],
    "wof:name":"Guiliguiste",
    "wof:placetype":"locality"
},
  "geometry": {"coordinates":[-88.95,13.85],"type":"Point"}
}