{
  "type": "Feature",
  "properties": {
    "gn:admin1_code":"06",
    "gn:asciiname":"San Jose La Montana",
    "gn:cc2":"SV",
    "gn:country_code":"SV",
    "gn:dem":809,
    "gn:feature_class":"P",
    "gn:feature_code":"PPL",
    "gn:name":"San Jos\u00e9 La Monta\u00f1a",
    "gn:population":0,
    "gn:timezone":"America/El_Salvador",
    "iso:country":"SV",
    "name:und_x_variant":[
        "San Jos\u00e9 de La Monta\u00f1a",
        "San Jos\u00e9 La Monta\u00f1a"
    ],
    "wof:name":"San Jose La Montana",
    "wof:placetype":"locality"
},
  "geometry": {"coordinates":[-89.05333,13.61639],"type":"Point"}
}