{
  "type": "Feature",
  "properties": {
    "gn:admin1_code":"9.0",
    "gn:asciiname":"Altos del Mora",
    "gn:country_code":"SV",
    "gn:dem":81,
    "gn:feature_class":"P",
    "gn:feature_code":"PPL",
    "gn:name":"Altos del Mora",
    "gn:population":0,
    "gn:timezone":"America/El_Salvador",
    "iso:country":"SV",
    "wof:name":"Altos del Mora",
    "wof:placetype":"locality"
},
  "geometry": {"coordinates":[-88.08444,13.41167],"type":"Point"}
}