{
  "type": "Feature",
  "properties": {
    "gn:admin1_code":"13",
    "gn:asciiname":"San Juan de Dios",
    "gn:country_code":"SV",
    "gn:dem":1330,
    "gn:feature_class":"P",
    "gn:feature_code":"PPL",
    "gn:name":"San Juan de Dios",
    "gn:population":0,
    "gn:timezone":"America/El_Salvador",
    "iso:country":"SV",
    "name:urd_x_preferred":[
        "\u0633\u0627\u0646 \u062e\u0648\u0622\u0646 \u062f\u06d2 \u062f\u06cc\u0648\u0633"
    ],
    "wof:name":"San Juan de Dios",
    "wof:placetype":"locality"
},
  "geometry": {"coordinates":[-89.7675,13.87944],"type":"Point"}
}