{
  "type": "Feature",
  "properties": {
    "gn:admin1_code":"08",
    "gn:asciiname":"Guacamaya",
    "gn:country_code":"SV",
    "gn:dem":515,
    "gn:feature_class":"P",
    "gn:feature_code":"PPL",
    "gn:name":"Guacamaya",
    "gn:population":0,
    "gn:timezone":"America/El_Salvador",
    "iso:country":"SV",
    "wof:name":"Guacamaya",
    "wof:placetype":"locality"
},
  "geometry": {"coordinates":[-88.11667,13.86667],"type":"Point"}
}