{
  "type": "Feature",
  "properties": {
    "iso:country":"SV",
    "name:chi_x_preferred":[
        "\u8056\u4f69\u5fb7\u7f85\u99ac\u85a9\u74e6\u7279"
    ],
    "name:dut_x_preferred":[
        "San Pedro Masahuat"
    ],
    "name:eng_x_preferred":[
        "San Pedro Masahuat"
    ],
    "name:fra_x_preferred":[
        "San Pedro Masahuat"
    ],
    "name:fre_x_preferred":[
        "San Pedro Masahuat"
    ],
    "name:ita_x_preferred":[
        "San Pedro Masahuat"
    ],
    "name:jpn_x_preferred":[
        "\u30b5\u30f3\u30fb\u30da\u30c9\u30ed\u30fb\u30de\u30b5\u30ef\u30c3\u30c8"
    ],
    "name:por_x_preferred":[
        "San Pedro Masahuat"
    ],
    "name:spa_x_preferred":[
        "San Pedro Masahuat"
    ],
    "name:zho_x_preferred":[
        "\u8056\u4f69\u5fb7\u7f85\u99ac\u85a9\u74e6\u7279"
    ],
    "qs:gn_country":"SV",
    "qs:gn_fcode":"PPL",
    "qs:gn_pop":2654,
    "qs:name":"San Pedro Masahuat",
    "qs:name_adm0":"El Salvador",
    "qs:name_adm1":"La Paz",
    "qs:photos":0,
    "qs:photos_1k":0,
    "qs:photos_9k":1,
    "qs:photos_9r":1,
    "qs:photos_all":8,
    "qs:photos_sr":0,
    "qs:placetype":"Town",
    "qs:pop_sr":"4",
    "qs:woe_adm0":23424807,
    "wd:wordcount":14,
    "wof:name":"San Pedro Masahuat",
    "wof:placetype":"locality",
    "wof:population":2654
},
  "geometry": {"coordinates":[-89.03861000000001,13.54361],"type":"Point"}
}