{
  "type": "Feature",
  "properties": {
    "gn:admin1_code":"14",
    "gn:asciiname":"San Buenaventura",
    "gn:cc2":"SV",
    "gn:country_code":"SV",
    "gn:dem":432,
    "gn:feature_class":"P",
    "gn:feature_code":"PPL",
    "gn:name":"San Buenaventura",
    "gn:population":0,
    "gn:timezone":"America/El_Salvador",
    "iso:country":"SV",
    "name:ceb_x_preferred":[
        "San Buenaventura"
    ],
    "name:ita_x_preferred":[
        "San Buenaventura"
    ],
    "name:por_x_preferred":[
        "San Buenaventura"
    ],
    "name:spa_x_preferred":[
        "San Buenaventura"
    ],
    "name:und_x_variant":[
        "San Buena",
        "San Buenaventura"
    ],
    "name:zho_x_preferred":[
        "\u8056\u5e03\u57c3\u7d0d\u6587\u5716\u62c9"
    ],
    "wof:name":"San Buenaventura",
    "wof:placetype":"locality"
},
  "geometry": {"coordinates":[-88.38333,13.53333],"type":"Point"}
}