{
  "type": "Feature",
  "properties": {
    "gn:admin1_code":"10",
    "gn:asciiname":"Las Victorias",
    "gn:cc2":"SV",
    "gn:country_code":"SV",
    "gn:dem":628,
    "gn:feature_class":"P",
    "gn:feature_code":"PPL",
    "gn:name":"Las Victorias",
    "gn:population":0,
    "gn:timezone":"America/El_Salvador",
    "iso:country":"SV",
    "name:fra_x_preferred":[
        "Las Victorias"
    ],
    "name:spa_x_preferred":[
        "Parque nacional Las Victorias"
    ],
    "name:und_x_variant":[
        "Colonia Las Victorias",
        "Barrio Victorias",
        "Victorias"
    ],
    "wof:name":"Las Victorias",
    "wof:placetype":"locality"
},
  "geometry": {"coordinates":[-89.16667,13.71667],"type":"Point"}
}