{
  "type": "Feature",
  "properties": {
    "gn:admin1_code":"10",
    "gn:asciiname":"El Guaje",
    "gn:country_code":"SV",
    "gn:dem":659,
    "gn:feature_class":"P",
    "gn:feature_code":"PPL",
    "gn:name":"El Guaje",
    "gn:population":0,
    "gn:timezone":"America/El_Salvador",
    "iso:country":"SV",
    "wof:name":"El Guaje",
    "wof:placetype":"locality"
},
  "geometry": {"coordinates":[-89.14055999999999,13.68278],"type":"Point"}
}