{
  "type": "Feature",
  "properties": {
    "gn:admin1_code":"04",
    "gn:asciiname":"San Bartolome Perulapia",
    "gn:cc2":"SV",
    "gn:country_code":"SV",
    "gn:dem":648,
    "gn:feature_class":"P",
    "gn:feature_code":"PPL",
    "gn:name":"San Bartolom\u00e9 Perulap\u00eda",
    "gn:population":0,
    "gn:timezone":"America/El_Salvador",
    "iso:country":"SV",
    "name:und_x_variant":[
        "Perulapia",
        "San Bartolom\u00e9 Perulap\u00eda"
    ],
    "wof:name":"San Bartolome Perulapia",
    "wof:placetype":"locality"
},
  "geometry": {"coordinates":[-89.05083,13.76583],"type":"Point"}
}