{
  "type": "Feature",
  "properties": {
    "gn:admin1_code":"04",
    "gn:asciiname":"San Bartolome Perulapia",
    "gn:cc2":"SV",
    "gn:country_code":"SV",
    "gn:dem":648,
    "gn:feature_class":"P",
    "gn:feature_code":"PPL",
    "gn:name":"San Bartolom\u00e9 Perulap\u00eda",
    "gn:population":0,
    "gn:timezone":"America/El_Salvador",
    "iso:country":"SV",
    "name:ceb_x_preferred":[
        "San Bartolom\u00e9 Perulap\u00eda"
    ],
    "name:ita_x_preferred":[
        "San Bartolom\u00e9 Perulap\u00eda"
    ],
    "name:por_x_preferred":[
        "San Bartolom\u00e9 Perulap\u00eda"
    ],
    "name:spa_x_preferred":[
        "San Bartolom\u00e9 Perulap\u00eda"
    ],
    "name:und_x_variant":[
        "Perulapia"
    ],
    "name:zho_x_preferred":[
        "\u8056\u5df4\u6258\u6d1b\u6885\u4f69\u9b6f\u62c9\u76ae\u4e9e"
    ],
    "wof:name":"San Bartolome Perulapia",
    "wof:placetype":"locality"
},
  "geometry": {"coordinates":[-89.05083,13.76583],"type":"Point"}
}