{
  "type": "Feature",
  "properties": {
    "gn:admin1_code":"10",
    "gn:asciiname":"El Tejar",
    "gn:country_code":"SV",
    "gn:dem":638,
    "gn:feature_class":"P",
    "gn:feature_code":"PPL",
    "gn:name":"El Tejar",
    "gn:population":0,
    "gn:timezone":"America/El_Salvador",
    "iso:country":"SV",
    "name:ceb_x_preferred":[
        "El Tejar"
    ],
    "name:fra_x_preferred":[
        "El Tejar"
    ],
    "name:ita_x_preferred":[
        "El Tejar"
    ],
    "name:spa_x_preferred":[
        "El Tejar"
    ],
    "name:swe_x_preferred":[
        "El Tejar"
    ],
    "wof:name":"El Tejar",
    "wof:placetype":"locality"
},
  "geometry": {"coordinates":[-89.18333,13.68333],"type":"Point"}
}