{
  "type": "Feature",
  "properties": {
    "gn:admin1_code":"11.0",
    "gn:asciiname":"Caserio La Joya",
    "gn:country_code":"SV",
    "gn:dem":722,
    "gn:feature_class":"P",
    "gn:feature_code":"PPL",
    "gn:name":"Caser\u00edo La Joya",
    "gn:population":0,
    "gn:timezone":"America/El_Salvador",
    "iso:country":"SV",
    "wof:name":"Caserio La Joya",
    "wof:placetype":"locality"
},
  "geometry": {"coordinates":[-89.65278000000001,14.18472],"type":"Point"}
}