{
  "type": "Feature",
  "properties": {
    "gn:admin1_code":"11",
    "gn:asciiname":"El Zompopo",
    "gn:cc2":"SV",
    "gn:country_code":"SV",
    "gn:dem":630,
    "gn:feature_class":"P",
    "gn:feature_code":"PPL",
    "gn:name":"El Zompopo",
    "gn:population":0,
    "gn:timezone":"America/El_Salvador",
    "iso:country":"SV",
    "name:und_x_variant":[
        "Caser\u00edo El Zompopo",
        "El Zompopo"
    ],
    "wof:name":"El Zompopo",
    "wof:placetype":"locality"
},
  "geometry": {"coordinates":[-89.45,14.15],"type":"Point"}
}