{
  "type": "Feature",
  "properties": {
    "iso:country":"SV",
    "name:ceb_x_preferred":[
        "Perqu\u00edn"
    ],
    "name:eng_x_preferred":[
        "Perqu\u00edn"
    ],
    "name:fra_x_preferred":[
        "Perqu\u00edn"
    ],
    "name:ita_x_preferred":[
        "Perqu\u00edn"
    ],
    "name:jpn_x_preferred":[
        "\u30da\u30eb\u30ad\u30f3"
    ],
    "name:nld_x_preferred":[
        "Perqu\u00edn"
    ],
    "name:por_x_preferred":[
        "Perqu\u00edn"
    ],
    "name:spa_x_preferred":[
        "Perqu\u00edn"
    ],
    "name:zho_x_preferred":[
        "\u4f69\u723e\u91d1"
    ],
    "qs:gn_country":"SV",
    "qs:gn_fcode":"PPL",
    "qs:gn_pop":0,
    "qs:name":"Perqu\u00edn",
    "qs:name_adm0":"El Salvador",
    "qs:name_adm1":"Moraz\u00e1n",
    "qs:photos":241,
    "qs:photos_1k":49,
    "qs:photos_9k":1,
    "qs:photos_9r":4,
    "qs:photos_all":241,
    "qs:photos_sr":4,
    "qs:placetype":"Town",
    "qs:pop_sr":"0",
    "qs:woe_adm0":23424807,
    "wof:name":"Perqu\u00edn",
    "wof:placetype":"locality"
},
  "geometry": {"coordinates":[-88.16667,13.95],"type":"Point"}
}