{
  "type": "Feature",
  "properties": {
    "gn:admin1_code":"07",
    "gn:asciiname":"Las Hojas",
    "gn:cc2":"SV",
    "gn:country_code":"SV",
    "gn:dem":299,
    "gn:feature_class":"P",
    "gn:feature_code":"PPL",
    "gn:name":"Las Hojas",
    "gn:population":0,
    "gn:timezone":"America/El_Salvador",
    "iso:country":"SV",
    "name:und_x_variant":[
        "Valle Las Hojas",
        "Las Hojas"
    ],
    "wof:name":"Las Hojas",
    "wof:placetype":"locality"
},
  "geometry": {"coordinates":[-88.01666999999998,13.55],"type":"Point"}
}