{
  "type": "Feature",
  "properties": {
    "gn:admin1_code":"13",
    "gn:asciiname":"La Puerta",
    "gn:cc2":"SV",
    "gn:country_code":"SV",
    "gn:dem":618,
    "gn:feature_class":"P",
    "gn:feature_code":"PPL",
    "gn:name":"La Puerta",
    "gn:population":0,
    "gn:timezone":"America/El_Salvador",
    "iso:country":"SV",
    "name:ceb_x_preferred":[
        "La Puerta"
    ],
    "name:deu_x_preferred":[
        "La Puerta"
    ],
    "name:fra_x_preferred":[
        "La Puerta"
    ],
    "name:ita_x_preferred":[
        "La Puerta"
    ],
    "name:por_x_preferred":[
        "La Puerta"
    ],
    "name:spa_x_preferred":[
        "La Puerta"
    ],
    "name:swe_x_preferred":[
        "La Puerta"
    ],
    "name:und_x_variant":[
        "Caser\u00edo La Puerta"
    ],
    "name:zho_x_preferred":[
        "\u62c9\u666e\u57c3\u723e\u5854"
    ],
    "wof:name":"La Puerta",
    "wof:placetype":"locality"
},
  "geometry": {"coordinates":[-89.53222,13.73306],"type":"Point"}
}