{
  "type": "Feature",
  "properties": {
    "gn:admin1_code":"12",
    "gn:asciiname":"Aradillas",
    "gn:cc2":"SV",
    "gn:country_code":"SV",
    "gn:dem":122,
    "gn:feature_class":"P",
    "gn:feature_code":"PPL",
    "gn:name":"Aradillas",
    "gn:population":0,
    "gn:timezone":"America/El_Salvador",
    "iso:country":"SV",
    "name:und_x_variant":[
        "Las Aradillas",
        "Aradillas"
    ],
    "wof:name":"Aradillas",
    "wof:placetype":"locality"
},
  "geometry": {"coordinates":[-88.63333,13.76667],"type":"Point"}
}