{
  "type": "Feature",
  "properties": {
    "gn:admin1_code":"9.0",
    "gn:asciiname":"Alto del Llano",
    "gn:country_code":"SV",
    "gn:dem":121,
    "gn:feature_class":"P",
    "gn:feature_code":"PPL",
    "gn:name":"Alto del Llano",
    "gn:population":0,
    "gn:timezone":"America/El_Salvador",
    "iso:country":"SV",
    "wof:name":"Alto del Llano",
    "wof:placetype":"locality"
},
  "geometry": {"coordinates":[-88.18611,13.4275],"type":"Point"}
}