{
  "type": "Feature",
  "properties": {
    "gn:admin1_code":"12",
    "gn:asciiname":"El Cimarron",
    "gn:cc2":"SV",
    "gn:country_code":"SV",
    "gn:dem":301,
    "gn:feature_class":"P",
    "gn:feature_code":"PPL",
    "gn:name":"El Cimarr\u00f3n",
    "gn:population":0,
    "gn:timezone":"America/El_Salvador",
    "iso:country":"SV",
    "name:und_x_variant":[
        "Cimarron",
        "El Cimarr\u00f3n"
    ],
    "wof:name":"El Cimarron",
    "wof:placetype":"locality"
},
  "geometry": {"coordinates":[-88.58333,13.61667],"type":"Point"}
}