{
  "type": "Feature",
  "properties": {
    "gn:admin1_code":"12",
    "gn:asciiname":"Hacienda El Triunfo",
    "gn:cc2":"SV",
    "gn:country_code":"SV",
    "gn:dem":11,
    "gn:feature_class":"P",
    "gn:feature_code":"PPL",
    "gn:name":"Hacienda El Triunfo",
    "gn:population":0,
    "gn:timezone":"America/El_Salvador",
    "iso:country":"SV",
    "name:und_x_variant":[
        "El Triunfo",
        "Hacienda El Triunfo"
    ],
    "wof:name":"Hacienda El Triunfo",
    "wof:placetype":"locality"
},
  "geometry": {"coordinates":[-88.73333000000002,13.38333],"type":"Point"}
}