{
  "type": "Feature",
  "properties": {
    "gn:admin1_code":"03",
    "gn:asciiname":"Los Filos",
    "gn:country_code":"SV",
    "gn:dem":753,
    "gn:feature_class":"P",
    "gn:feature_code":"PPL",
    "gn:name":"Los Filos",
    "gn:population":0,
    "gn:timezone":"America/El_Salvador",
    "iso:country":"SV",
    "wof:name":"Los Filos",
    "wof:placetype":"locality"
},
  "geometry": {"coordinates":[-88.73333000000002,14.08333],"type":"Point"}
}