{
  "type": "Feature",
  "properties": {
    "gn:admin1_code":"09",
    "gn:asciiname":"Puerto Viejo",
    "gn:country_code":"SV",
    "gn:dem":82,
    "gn:feature_class":"P",
    "gn:feature_code":"PPL",
    "gn:name":"Puerto Viejo",
    "gn:population":0,
    "gn:timezone":"America/El_Salvador",
    "iso:country":"SV",
    "name:ceb_x_preferred":[
        "Puerto Viejo"
    ],
    "name:nor_x_preferred":[
        "Puerto Viejo"
    ],
    "name:spa_x_preferred":[
        "Puerto Viejo"
    ],
    "name:swe_x_preferred":[
        "Puerto Viejo"
    ],
    "wof:name":"Puerto Viejo",
    "wof:placetype":"locality"
},
  "geometry": {"coordinates":[-88.05028,13.28028],"type":"Point"}
}