{
  "type": "Feature",
  "properties": {
    "gn:admin1_code":"07",
    "gn:asciiname":"Agua Fria",
    "gn:country_code":"SV",
    "gn:dem":356,
    "gn:feature_class":"P",
    "gn:feature_code":"PPL",
    "gn:name":"Agua Fr\u00eda",
    "gn:population":0,
    "gn:timezone":"America/El_Salvador",
    "iso:country":"SV",
    "wof:name":"Agua Fria",
    "wof:placetype":"locality"
},
  "geometry": {"coordinates":[-87.90000000000001,13.78333],"type":"Point"}
}