{
  "type": "Feature",
  "properties": {
    "iso:country":"SV",
    "name:chi_x_preferred":[
        "\u6d1b\u6d1b\u8482\u514b"
    ],
    "name:dut_x_preferred":[
        "Lolotique"
    ],
    "name:eng_x_preferred":[
        "Lolotique"
    ],
    "name:fre_x_preferred":[
        "Lolotique"
    ],
    "name:ita_x_preferred":[
        "Lolotique"
    ],
    "name:jpn_x_preferred":[
        "\u30ed\u30ed\u30c6\u30a3\u30b1"
    ],
    "name:por_x_preferred":[
        "Lolotique"
    ],
    "name:spa_x_preferred":[
        "Lolotique"
    ],
    "name:zho_x_preferred":[
        "\u6d1b\u6d1b\u8482\u514b"
    ],
    "qs:gn_country":"SV",
    "qs:gn_fcode":"PPL",
    "qs:gn_pop":2654,
    "qs:name":"Lolotique",
    "qs:name_adm0":"El Salvador",
    "qs:name_adm1":"San Miguel",
    "qs:photos":0,
    "qs:photos_1k":0,
    "qs:photos_9k":1,
    "qs:photos_9r":1,
    "qs:photos_all":3,
    "qs:photos_sr":0,
    "qs:placetype":"Town",
    "qs:pop_sr":"4",
    "qs:woe_adm0":23424807,
    "wd:wordcount":29,
    "wof:name":"Lolotique",
    "wof:placetype":"locality",
    "wof:population":2654
},
  "geometry": {"coordinates":[-88.34999999999999,13.55],"type":"Point"}
}