{
  "type": "Feature",
  "properties": {
    "gn:admin1_code":"07",
    "gn:asciiname":"Palo Blanco",
    "gn:country_code":"SV",
    "gn:dem":65,
    "gn:feature_class":"P",
    "gn:feature_code":"PPL",
    "gn:name":"Palo Blanco",
    "gn:population":0,
    "gn:timezone":"America/El_Salvador",
    "iso:country":"SV",
    "wof:name":"Palo Blanco",
    "wof:placetype":"locality"
},
  "geometry": {"coordinates":[-87.86667,13.53333],"type":"Point"}
}