{
  "type": "Feature",
  "properties": {
    "gn:admin1_code":"07",
    "gn:asciiname":"El Tizate",
    "gn:cc2":"SV",
    "gn:country_code":"SV",
    "gn:dem":159,
    "gn:feature_class":"P",
    "gn:feature_code":"PPL",
    "gn:name":"El Tizate",
    "gn:population":0,
    "gn:timezone":"America/El_Salvador",
    "iso:country":"SV",
    "name:und_x_variant":[
        "El Tizatillo",
        "El Tizate"
    ],
    "wof:name":"El Tizate",
    "wof:placetype":"locality"
},
  "geometry": {"coordinates":[-87.96583000000003,13.48083],"type":"Point"}
}