{
  "type": "Feature",
  "properties": {
    "gn:admin1_code":"12",
    "gn:asciiname":"Dos Quebradas",
    "gn:cc2":"SV",
    "gn:country_code":"SV",
    "gn:dem":356,
    "gn:feature_class":"P",
    "gn:feature_code":"PPL",
    "gn:name":"Dos Quebradas",
    "gn:population":0,
    "gn:timezone":"America/El_Salvador",
    "iso:country":"SV",
    "name:und_x_variant":[
        "Cant\u00f3n Dos Quebradas",
        "Dos Quebradas"
    ],
    "wof:name":"Dos Quebradas",
    "wof:placetype":"locality"
},
  "geometry": {"coordinates":[-88.76666999999998,13.61667],"type":"Point"}
}