{
  "type": "Feature",
  "properties": {
    "gn:admin1_code":"11.0",
    "gn:asciiname":"Calzontes Abajo",
    "gn:country_code":"SV",
    "gn:dem":881,
    "gn:feature_class":"P",
    "gn:feature_code":"PPL",
    "gn:name":"Calzontes Abajo",
    "gn:population":0,
    "gn:timezone":"America/El_Salvador",
    "iso:country":"SV",
    "wof:name":"Calzontes Abajo",
    "wof:placetype":"locality"
},
  "geometry": {"coordinates":[-89.58166999999997,13.93528],"type":"Point"}
}