{
  "type": "Feature",
  "properties": {
    "gn:admin1_code":"02",
    "gn:asciiname":"El Cimarron",
    "gn:cc2":"SV",
    "gn:country_code":"SV",
    "gn:dem":264,
    "gn:feature_class":"P",
    "gn:feature_code":"PPL",
    "gn:name":"El Cimarr\u00f3n",
    "gn:population":0,
    "gn:timezone":"America/El_Salvador",
    "iso:country":"SV",
    "name:und_x_variant":[
        "Cimarr\u00f3n",
        "El Cimarr\u00f3n"
    ],
    "wof:name":"El Cimarron",
    "wof:placetype":"locality"
},
  "geometry": {"coordinates":[-88.66667,13.98333],"type":"Point"}
}