{
  "type": "Feature",
  "properties": {
    "gn:admin1_code":"11",
    "gn:asciiname":"Lagnetas",
    "gn:country_code":"SV",
    "gn:dem":695,
    "gn:feature_class":"P",
    "gn:feature_code":"PPL",
    "gn:name":"Lagnetas",
    "gn:population":0,
    "gn:timezone":"America/El_Salvador",
    "iso:country":"SV",
    "wof:name":"Lagnetas",
    "wof:placetype":"locality"
},
  "geometry": {"coordinates":[-89.34999999999999,14.25],"type":"Point"}
}