{
  "type": "Feature",
  "properties": {
    "gn:admin1_code":"07",
    "gn:asciiname":"Barrancones",
    "gn:country_code":"SV",
    "gn:dem":3,
    "gn:feature_class":"P",
    "gn:feature_code":"PPL",
    "gn:name":"Barrancones",
    "gn:population":0,
    "gn:timezone":"America/El_Salvador",
    "iso:country":"SV",
    "wof:name":"Barrancones",
    "wof:placetype":"locality"
},
  "geometry": {"coordinates":[-87.79083,13.43361],"type":"Point"}
}