{
  "type": "Feature",
  "properties": {
    "gn:admin1_code":"07",
    "gn:asciiname":"Candelaria Albornoz",
    "gn:country_code":"SV",
    "gn:dem":239,
    "gn:feature_class":"P",
    "gn:feature_code":"PPL",
    "gn:name":"Candelaria Albornoz",
    "gn:population":0,
    "gn:timezone":"America/El_Salvador",
    "iso:country":"SV",
    "wof:name":"Candelaria Albornoz",
    "wof:placetype":"locality"
},
  "geometry": {"coordinates":[-87.94694,13.60806],"type":"Point"}
}