{
  "type": "Feature",
  "properties": {
    "iso:country":"SV",
    "name:eng_x_preferred":[
        "Spodnja \u0160i\u0161ka"
    ],
    "name:fra_x_preferred":[
        "Spodnja \u0160i\u0161ka"
    ],
    "name:slv_x_preferred":[
        "Spodnja \u0160i\u0161ka"
    ],
    "name:und_x_colloquial":[
        "Spodnja Siska"
    ],
    "name:und_x_preferred":[
        "Spodnja \u0160i\u0161ka"
    ],
    "name:unk_x_variant":[
        "Spodnja \u0160i\u0161ka",
        "Spodnja \u0160i\u0161ka"
    ],
    "qs:gn_adm0_cc":"SI",
    "qs:gn_fcode":"PPLX",
    "qs:gn_local":3196359,
    "qs:gn_nam_loc":"Ljubljana, Ljubljana, Ljubljana, SI",
    "qs:gn_namadm1":"61",
    "qs:gn_name":"Spodnja \u0160i\u0161ka",
    "qs:local_max":13863,
    "qs:local_sum":25230,
    "qs:localhoods":13,
    "qs:name":"Spodnja \u0160i\u0161ka",
    "qs:name_adm0":"Slovenija",
    "qs:name_adm1":"Ljubljana",
    "qs:name_adm2":"Ljubljana",
    "qs:name_local":"Ljubljana",
    "qs:photo_max":311,
    "qs:photo_sum":725,
    "qs:placetype":"Suburb",
    "qs:quad_count":31,
    "qs:woe_adm0":23424945,
    "qs:woe_adm1":55848364,
    "qs:woe_adm2":12591568,
    "qs:woe_lau":0,
    "qs:woe_local":530634,
    "qs:woe_ver":"7.10.0",
    "wd:wordcount":475,
    "wof:lang":[
        "unk"
    ],
    "wof:name":"Spodnja Siska",
    "wof:placetype":"neighbourhood"
},
  "geometry": {"coordinates":[14.496426,46.065008],"type":"Point"}
}