{
  "type": "Feature",
  "properties": {
    "iso:country":"SV",
    "name:bel_x_variant":[
        "\u0406\u043b\u044f\u043f\u0430\u043d\u0433\u0430"
    ],
    "name:bul_x_preferred":[
        "\u0418\u043b\u043e\u043f\u0430\u043d\u0433\u043e"
    ],
    "name:ceb_x_preferred":[
        "Ilopango"
    ],
    "name:deu_x_preferred":[
        "Ilopango"
    ],
    "name:eng_x_preferred":[
        "Ilopango"
    ],
    "name:epo_x_preferred":[
        "Ilopango"
    ],
    "name:eus_x_preferred":[
        "Ilopango"
    ],
    "name:fra_x_preferred":[
        "Ilopango"
    ],
    "name:ita_x_preferred":[
        "Ilopango"
    ],
    "name:jpn_x_preferred":[
        "\u30a4\u30ed\u30d1\u30f3\u30b4"
    ],
    "name:nah_x_preferred":[
        "X\u012bl\u014dpanco"
    ],
    "name:nan_x_preferred":[
        "Ilopango"
    ],
    "name:nld_x_preferred":[
        "Ilopango"
    ],
    "name:nob_x_preferred":[
        "Ilopango"
    ],
    "name:pol_x_preferred":[
        "Ilopango"
    ],
    "name:por_x_preferred":[
        "Ilopango"
    ],
    "name:rus_x_preferred":[
        "\u0418\u043b\u043e\u043f\u0430\u043d\u0433\u043e"
    ],
    "name:spa_x_preferred":[
        "Ilopango"
    ],
    "name:srp_x_preferred":[
        "\u0418\u043b\u043e\u043f\u0430\u043d\u0433\u043e"
    ],
    "name:tat_x_preferred":[
        "\u0418\u043b\u043e\u043f\u0430\u043d\u0433\u043e"
    ],
    "name:und_x_variant":[
        "Ylopango"
    ],
    "name:urd_x_preferred":[
        "\u0627\u0644\u0648\u067e\u0627\u0646\u06af\u0648"
    ],
    "name:vie_x_preferred":[
        "Ilopango"
    ],
    "name:war_x_preferred":[
        "Ilopango"
    ],
    "name:zho_x_preferred":[
        "\u4f0a\u6d1b\u6f58\u6208"
    ],
    "qs:gn_country":"SV",
    "qs:gn_fcode":"PPL",
    "qs:gn_pop":38890,
    "qs:name":"Ilopango",
    "qs:name_adm0":"El Salvador",
    "qs:name_adm1":"San Salvador",
    "qs:photos":494,
    "qs:photos_1k":100,
    "qs:photos_9k":2,
    "qs:photos_9r":5,
    "qs:photos_all":494,
    "qs:photos_sr":7,
    "qs:placetype":"Town",
    "qs:pop_sr":"7",
    "qs:woe_adm0":23424807,
    "wof:name":"Ilopango",
    "wof:placetype":"locality",
    "wof:population":38890
},
  "geometry": {"coordinates":[-89.10944000000001,13.70167],"type":"Point"}
}