{
  "type": "Feature",
  "properties": {
    "gn:admin1_code":"06",
    "gn:asciiname":"El Chile",
    "gn:country_code":"SV",
    "gn:dem":903,
    "gn:feature_class":"P",
    "gn:feature_code":"PPL",
    "gn:name":"El Chile",
    "gn:population":0,
    "gn:timezone":"America/El_Salvador",
    "iso:country":"SV",
    "wof:name":"El Chile",
    "wof:placetype":"locality"
},
  "geometry": {"coordinates":[-88.88333,13.58333],"type":"Point"}
}