{
  "type": "Feature",
  "properties": {
    "gn:admin1_code":"09",
    "gn:asciiname":"Jocote Dulce",
    "gn:cc2":"SV",
    "gn:country_code":"SV",
    "gn:dem":856,
    "gn:feature_class":"P",
    "gn:feature_code":"PPL",
    "gn:name":"Jocote Dulce",
    "gn:population":0,
    "gn:timezone":"America/El_Salvador",
    "iso:country":"SV",
    "name:und_x_variant":[
        "El Jocote Dulce",
        "Jocote Dulce"
    ],
    "wof:name":"Jocote Dulce",
    "wof:placetype":"locality"
},
  "geometry": {"coordinates":[-88.34999999999999,13.46667],"type":"Point"}
}