{
  "type": "Feature",
  "properties": {
    "gn:admin1_code":"06",
    "gn:asciiname":"Espino Arriba",
    "gn:cc2":"SV",
    "gn:country_code":"SV",
    "gn:dem":254,
    "gn:feature_class":"P",
    "gn:feature_code":"PPL",
    "gn:name":"Espino Arriba",
    "gn:population":0,
    "gn:timezone":"America/El_Salvador",
    "iso:country":"SV",
    "name:und_x_variant":[
        "El Espino Arriba",
        "Espino Arriba"
    ],
    "wof:name":"Espino Arriba",
    "wof:placetype":"locality"
},
  "geometry": {"coordinates":[-88.86667,13.51667],"type":"Point"}
}