{
  "type": "Feature",
  "properties": {
    "gn:admin1_code":"03",
    "gn:asciiname":"El Roblito",
    "gn:country_code":"SV",
    "gn:dem":844,
    "gn:feature_class":"P",
    "gn:feature_code":"PPL",
    "gn:name":"El Roblito",
    "gn:population":0,
    "gn:timezone":"America/El_Salvador",
    "iso:country":"SV",
    "wof:name":"El Roblito",
    "wof:placetype":"locality"
},
  "geometry": {"coordinates":[-89.23333000000002,14.28333],"type":"Point"}
}