{
  "type": "Feature",
  "properties": {
    "gn:admin1_code":"12",
    "gn:asciiname":"El Junquillal",
    "gn:cc2":"SV",
    "gn:country_code":"SV",
    "gn:dem":467,
    "gn:feature_class":"P",
    "gn:feature_code":"PPL",
    "gn:name":"El Junquillal",
    "gn:population":0,
    "gn:timezone":"America/El_Salvador",
    "iso:country":"SV",
    "name:und_x_variant":[
        "Caser\u00edo El Junquillar",
        "Junquillar",
        "El Junquillal"
    ],
    "wof:name":"El Junquillal",
    "wof:placetype":"locality"
},
  "geometry": {"coordinates":[-88.66667,13.63333],"type":"Point"}
}