{
  "type": "Feature",
  "properties": {
    "gn:admin1_code":"05",
    "gn:asciiname":"El Jicaro",
    "gn:cc2":"SV",
    "gn:country_code":"SV",
    "gn:dem":498,
    "gn:feature_class":"P",
    "gn:feature_code":"PPL",
    "gn:name":"El J\u00edcaro",
    "gn:population":0,
    "gn:timezone":"America/El_Salvador",
    "iso:country":"SV",
    "name:und_x_variant":[
        "J\u00edcaro",
        "El J\u00edcaro"
    ],
    "wof:name":"El Jicaro",
    "wof:placetype":"locality"
},
  "geometry": {"coordinates":[-89.31333000000002,13.87],"type":"Point"}
}