{
  "type": "Feature",
  "properties": {
    "gn:admin1_code":"03",
    "gn:asciiname":"Los Martinez",
    "gn:country_code":"SV",
    "gn:dem":372,
    "gn:feature_class":"P",
    "gn:feature_code":"PPL",
    "gn:name":"Los Mart\u00ednez",
    "gn:population":0,
    "gn:timezone":"America/El_Salvador",
    "iso:country":"SV",
    "wof:name":"Los Martinez",
    "wof:placetype":"locality"
},
  "geometry": {"coordinates":[-89.08333,14.16667],"type":"Point"}
}