{
  "type": "Feature",
  "properties": {
    "gn:admin1_code":"10",
    "gn:asciiname":"Plan del Pino",
    "gn:country_code":"SV",
    "gn:dem":609,
    "gn:feature_class":"P",
    "gn:feature_code":"PPL",
    "gn:name":"Plan del Pino",
    "gn:population":0,
    "gn:timezone":"America/El_Salvador",
    "iso:country":"SV",
    "wof:name":"Plan del Pino",
    "wof:placetype":"locality"
},
  "geometry": {"coordinates":[-89.14194000000001,13.74083],"type":"Point"}
}