{
  "type": "Feature",
  "properties": {
    "gn:admin1_code":"08",
    "gn:asciiname":"Sicahuite",
    "gn:cc2":"SV",
    "gn:country_code":"SV",
    "gn:dem":467,
    "gn:feature_class":"P",
    "gn:feature_code":"PPL",
    "gn:name":"Sicahuite",
    "gn:population":0,
    "gn:timezone":"America/El_Salvador",
    "iso:country":"SV",
    "name:und_x_variant":[
        "Sicag\u00fcite",
        "Sicahuite"
    ],
    "wof:name":"Sicahuite",
    "wof:placetype":"locality"
},
  "geometry": {"coordinates":[-88.26666999999998,13.91667],"type":"Point"}
}