{
  "type": "Feature",
  "properties": {
    "gn:admin1_code":"01",
    "gn:asciiname":"El Barro",
    "gn:cc2":"SV",
    "gn:country_code":"SV",
    "gn:dem":845,
    "gn:feature_class":"P",
    "gn:feature_code":"PPL",
    "gn:name":"El Barro",
    "gn:population":0,
    "gn:timezone":"America/El_Salvador",
    "iso:country":"SV",
    "name:und_x_variant":[
        "Barro de Los Ausoles",
        "El Barro"
    ],
    "wof:name":"El Barro",
    "wof:placetype":"locality"
},
  "geometry": {"coordinates":[-89.82722,13.9125],"type":"Point"}
}