{
  "type": "Feature",
  "properties": {
    "gn:admin1_code":"06",
    "gn:asciiname":"Tacualuya",
    "gn:cc2":"SV",
    "gn:country_code":"SV",
    "gn:dem":37,
    "gn:feature_class":"P",
    "gn:feature_code":"PPL",
    "gn:name":"Tacualuya",
    "gn:population":0,
    "gn:timezone":"America/El_Salvador",
    "iso:country":"SV",
    "name:und_x_variant":[
        "Tecualuya",
        "Tacualuya"
    ],
    "wof:name":"Tacualuya",
    "wof:placetype":"locality"
},
  "geometry": {"coordinates":[-89.11055999999998,13.47389],"type":"Point"}
}