{
  "type": "Feature",
  "properties": {
    "gn:admin1_code":"11",
    "gn:asciiname":"San Jose Capulin",
    "gn:country_code":"SV",
    "gn:dem":493,
    "gn:feature_class":"P",
    "gn:feature_code":"PPL",
    "gn:name":"San Jos\u00e9 Capul\u00edn",
    "gn:population":0,
    "gn:timezone":"America/El_Salvador",
    "iso:country":"SV",
    "wof:name":"San Jose Capulin",
    "wof:placetype":"locality"
},
  "geometry": {"coordinates":[-89.38333,14.21667],"type":"Point"}
}