{
  "type": "Feature",
  "properties": {
    "gn:admin1_code":"03",
    "gn:asciiname":"Guachipilin",
    "gn:country_code":"SV",
    "gn:dem":558,
    "gn:feature_class":"P",
    "gn:feature_code":"PPL",
    "gn:name":"Guachipil\u00edn",
    "gn:population":0,
    "gn:timezone":"America/El_Salvador",
    "iso:country":"SV",
    "wof:name":"Guachipilin",
    "wof:placetype":"locality"
},
  "geometry": {"coordinates":[-88.96666999999999,14.16667],"type":"Point"}
}