{
  "type": "Feature",
  "properties": {
    "gn:admin1_code":"09",
    "gn:asciiname":"El Carao",
    "gn:country_code":"SV",
    "gn:dem":98,
    "gn:feature_class":"P",
    "gn:feature_code":"PPL",
    "gn:name":"El Carao",
    "gn:population":0,
    "gn:timezone":"America/El_Salvador",
    "iso:country":"SV",
    "wof:name":"El Carao",
    "wof:placetype":"locality"
},
  "geometry": {"coordinates":[-88.14416999999997,13.32306],"type":"Point"}
}