{
  "type": "Feature",
  "properties": {
    "gn:admin1_code":"08",
    "gn:asciiname":"Los Marquez",
    "gn:country_code":"SV",
    "gn:dem":718,
    "gn:feature_class":"P",
    "gn:feature_code":"PPL",
    "gn:name":"Los Marquez",
    "gn:population":0,
    "gn:timezone":"America/El_Salvador",
    "iso:country":"SV",
    "wof:name":"Los Marquez",
    "wof:placetype":"locality"
},
  "geometry": {"coordinates":[-88.15000000000001,13.73333],"type":"Point"}
}