{
  "type": "Feature",
  "properties": {
    "gn:admin1_code":"05",
    "gn:asciiname":"Boca Tronadora",
    "gn:country_code":"SV",
    "gn:dem":466,
    "gn:feature_class":"P",
    "gn:feature_code":"PPL",
    "gn:name":"Boca Tronadora",
    "gn:population":0,
    "gn:timezone":"America/El_Salvador",
    "iso:country":"SV",
    "wof:name":"Boca Tronadora",
    "wof:placetype":"locality"
},
  "geometry": {"coordinates":[-89.34444000000001,13.82944],"type":"Point"}
}