{
  "type": "Feature",
  "properties": {
    "gn:admin1_code":"10",
    "gn:asciiname":"La Fuente",
    "gn:cc2":"SV",
    "gn:country_code":"SV",
    "gn:dem":751,
    "gn:feature_class":"P",
    "gn:feature_code":"PPL",
    "gn:name":"La Fuente",
    "gn:population":0,
    "gn:timezone":"America/El_Salvador",
    "iso:country":"SV",
    "name:und_x_variant":[
        "Valle La Fuente",
        "La Fuente"
    ],
    "wof:name":"La Fuente",
    "wof:placetype":"locality"
},
  "geometry": {"coordinates":[-89.10778000000001,13.74444],"type":"Point"}
}