{
  "type": "Feature",
  "properties": {
    "gn:admin1_code":"08",
    "gn:asciiname":"Portillo Blanco",
    "gn:country_code":"SV",
    "gn:dem":348,
    "gn:feature_class":"P",
    "gn:feature_code":"PPL",
    "gn:name":"Portillo Blanco",
    "gn:population":0,
    "gn:timezone":"America/El_Salvador",
    "iso:country":"SV",
    "wof:name":"Portillo Blanco",
    "wof:placetype":"locality"
},
  "geometry": {"coordinates":[-88.13333,13.71667],"type":"Point"}
}