{
  "type": "Feature",
  "properties": {
    "gn:admin1_code":"12",
    "gn:asciiname":"San Jeronimo Limon",
    "gn:cc2":"SV",
    "gn:country_code":"SV",
    "gn:dem":586,
    "gn:feature_class":"P",
    "gn:feature_code":"PPL",
    "gn:name":"San Jer\u00f3nimo Lim\u00f3n",
    "gn:population":0,
    "gn:timezone":"America/El_Salvador",
    "iso:country":"SV",
    "name:und_x_variant":[
        "Cant\u00f3n San Jer\u00f3nimo",
        "El Lim\u00f3n",
        "San Jer\u00f3nimo",
        "San Jer\u00f3nimo Lim\u00f3n"
    ],
    "wof:name":"San Jeronimo Limon",
    "wof:placetype":"locality"
},
  "geometry": {"coordinates":[-88.88333,13.65],"type":"Point"}
}