{
  "type": "Feature",
  "properties": {
    "gn:admin1_code":"11",
    "gn:asciiname":"Aldea San Antonio",
    "gn:country_code":"SV",
    "gn:dem":681,
    "gn:feature_class":"P",
    "gn:feature_code":"PPL",
    "gn:name":"Aldea San Antonio",
    "gn:population":0,
    "gn:timezone":"America/El_Salvador",
    "iso:country":"SV",
    "name:ceb_x_preferred":[
        "Aldea San Antonio"
    ],
    "name:fas_x_preferred":[
        "\u0627\u0644\u062f\u06cc\u0627 \u0633\u0627\u0646 \u0627\u0646\u062a\u0648\u0646\u06cc\u0648"
    ],
    "name:por_x_preferred":[
        "Aldea San Antonio"
    ],
    "name:spa_x_preferred":[
        "Aldea San Antonio"
    ],
    "name:swe_x_preferred":[
        "Aldea San Antonio"
    ],
    "wof:name":"Aldea San Antonio",
    "wof:placetype":"locality"
},
  "geometry": {"coordinates":[-89.56667,13.98333],"type":"Point"}
}