{
  "type": "Feature",
  "properties": {
    "gn:admin1_code":"11",
    "gn:asciiname":"La Libertad",
    "gn:cc2":"SV",
    "gn:country_code":"SV",
    "gn:dem":753,
    "gn:feature_class":"P",
    "gn:feature_code":"PPL",
    "gn:name":"La Libertad",
    "gn:population":0,
    "gn:timezone":"America/El_Salvador",
    "iso:country":"SV",
    "name:und_x_variant":[
        "Cant\u00f3n Libertad",
        "Libertad",
        "La Libertad"
    ],
    "wof:name":"La Libertad",
    "wof:placetype":"locality"
},
  "geometry": {"coordinates":[-89.68444000000002,13.97167],"type":"Point"}
}