{
  "type": "Feature",
  "properties": {
    "gn:admin1_code":"03",
    "gn:asciiname":"Vainillas",
    "gn:country_code":"SV",
    "gn:dem":960,
    "gn:feature_class":"P",
    "gn:feature_code":"PPL",
    "gn:name":"Vainillas",
    "gn:population":0,
    "gn:timezone":"America/El_Salvador",
    "iso:country":"SV",
    "wof:name":"Vainillas",
    "wof:placetype":"locality"
},
  "geometry": {"coordinates":[-88.91667,14.16667],"type":"Point"}
}