{
  "type": "Feature",
  "properties": {
    "gn:admin1_code":"07",
    "gn:asciiname":"El Penon",
    "gn:country_code":"SV",
    "gn:dem":179,
    "gn:feature_class":"P",
    "gn:feature_code":"PPL",
    "gn:name":"El Pe\u00f1\u00f3n",
    "gn:population":0,
    "gn:timezone":"America/El_Salvador",
    "iso:country":"SV",
    "wof:name":"El Penon",
    "wof:placetype":"locality"
},
  "geometry": {"coordinates":[-87.78333000000001,13.61667],"type":"Point"}
}