{
  "type": "Feature",
  "properties": {
    "gn:admin1_code":"1.0",
    "gn:asciiname":"La Cuchilla",
    "gn:country_code":"SV",
    "gn:dem":29,
    "gn:feature_class":"P",
    "gn:feature_code":"PPL",
    "gn:name":"La Cuchilla",
    "gn:population":0,
    "gn:timezone":"America/El_Salvador",
    "iso:country":"SV",
    "wof:name":"La Cuchilla",
    "wof:placetype":"locality"
},
  "geometry": {"coordinates":[-90.05306,13.81111],"type":"Point"}
}