{
  "type": "Feature",
  "properties": {
    "gn:admin1_code":"09",
    "gn:asciiname":"Candelaria",
    "gn:country_code":"SV",
    "gn:dem":396,
    "gn:feature_class":"P",
    "gn:feature_code":"PPL",
    "gn:name":"Candelaria",
    "gn:population":0,
    "gn:timezone":"America/El_Salvador",
    "iso:country":"SV",
    "wof:name":"Candelaria",
    "wof:placetype":"locality"
},
  "geometry": {"coordinates":[-88.36667,13.43333],"type":"Point"}
}