{
  "type": "Feature",
  "properties": {
    "gn:admin1_code":"09",
    "gn:asciiname":"Candelaria",
    "gn:country_code":"SV",
    "gn:dem":396,
    "gn:feature_class":"P",
    "gn:feature_code":"PPL",
    "gn:name":"Candelaria",
    "gn:population":0,
    "gn:timezone":"America/El_Salvador",
    "iso:country":"SV",
    "name:bpy_x_preferred":[
        "\u0995\u09be\u09a8\u09a1\u09c7\u09b2\u09be\u09b0\u09bf\u09af\u09bc\u09be"
    ],
    "name:ceb_x_preferred":[
        "Candelaria"
    ],
    "name:ces_x_preferred":[
        "Candelaria"
    ],
    "name:deu_x_preferred":[
        "Candelaria"
    ],
    "name:epo_x_preferred":[
        "Candelaria"
    ],
    "name:eus_x_preferred":[
        "Candelaria"
    ],
    "name:fra_x_preferred":[
        "Candelaria"
    ],
    "name:ita_x_preferred":[
        "Candelaria"
    ],
    "name:msa_x_preferred":[
        "Candelaria"
    ],
    "name:nld_x_preferred":[
        "Candelaria"
    ],
    "name:nor_x_preferred":[
        "Candelaria"
    ],
    "name:pol_x_preferred":[
        "Candelaria"
    ],
    "name:ron_x_preferred":[
        "Candelaria"
    ],
    "name:rus_x_preferred":[
        "\u041a\u0430\u043d\u0434\u0435\u043b\u0430\u0440\u0438\u044f"
    ],
    "name:sco_x_preferred":[
        "Candelaria"
    ],
    "name:spa_x_preferred":[
        "Candelaria"
    ],
    "name:swe_x_preferred":[
        "Candelaria"
    ],
    "name:vie_x_preferred":[
        "Candelaria"
    ],
    "name:war_x_preferred":[
        "Candelaria"
    ],
    "name:zho_x_preferred":[
        "\u574e\u5fb7\u62c9\u91cc\u4e9a"
    ],
    "wof:name":"Candelaria",
    "wof:placetype":"locality"
},
  "geometry": {"coordinates":[-88.36667,13.43333],"type":"Point"}
}