{
  "type": "Feature",
  "properties": {
    "gn:admin1_code":"04",
    "gn:asciiname":"San Ramon",
    "gn:country_code":"SV",
    "gn:dem":575,
    "gn:feature_class":"P",
    "gn:feature_code":"PPL",
    "gn:name":"San Ram\u00f3n",
    "gn:population":0,
    "gn:timezone":"America/El_Salvador",
    "iso:country":"SV",
    "name:und_x_variant":[
        "San Ram\u00f3n"
    ],
    "wof:name":"San Ramon",
    "wof:placetype":"locality"
},
  "geometry": {"coordinates":[-88.93333,13.68333],"type":"Point"}
}