{
  "type": "Feature",
  "properties": {
    "gn:admin1_code":"09",
    "gn:asciiname":"San Julian",
    "gn:country_code":"SV",
    "gn:dem":424,
    "gn:feature_class":"P",
    "gn:feature_code":"PPL",
    "gn:name":"San Juli\u00e1n",
    "gn:population":0,
    "gn:timezone":"America/El_Salvador",
    "iso:country":"SV",
    "wof:name":"San Julian",
    "wof:placetype":"locality"
},
  "geometry": {"coordinates":[-88.34999999999999,13.43333],"type":"Point"}
}