{
  "type": "Feature",
  "properties": {
    "gn:admin1_code":"11",
    "gn:asciiname":"El Cambio",
    "gn:country_code":"SV",
    "gn:dem":590,
    "gn:feature_class":"P",
    "gn:feature_code":"PPL",
    "gn:name":"El Cambio",
    "gn:population":0,
    "gn:timezone":"America/El_Salvador",
    "iso:country":"SV",
    "wof:name":"El Cambio",
    "wof:placetype":"locality"
},
  "geometry": {"coordinates":[-89.47028,13.83194],"type":"Point"}
}