{
  "type": "Feature",
  "properties": {
    "gn:admin1_code":"01",
    "gn:asciiname":"San Ramoncito",
    "gn:country_code":"SV",
    "gn:dem":1500,
    "gn:feature_class":"P",
    "gn:feature_code":"PPL",
    "gn:name":"San Ramoncito",
    "gn:population":0,
    "gn:timezone":"America/El_Salvador",
    "iso:country":"SV",
    "wof:name":"San Ramoncito",
    "wof:placetype":"locality"
},
  "geometry": {"coordinates":[-89.81667,13.86667],"type":"Point"}
}