{
  "type": "Feature",
  "properties": {
    "gn:admin1_code":"02",
    "gn:asciiname":"Huiscoyol",
    "gn:cc2":"SV",
    "gn:country_code":"SV",
    "gn:dem":335,
    "gn:feature_class":"P",
    "gn:feature_code":"PPL",
    "gn:name":"Huiscoyol",
    "gn:population":0,
    "gn:timezone":"America/El_Salvador",
    "iso:country":"SV",
    "name:und_x_variant":[
        "El Huiscoyol",
        "Huiscoyo",
        "Huiscoyol"
    ],
    "wof:name":"Huiscoyol",
    "wof:placetype":"locality"
},
  "geometry": {"coordinates":[-88.93333,13.91667],"type":"Point"}
}