{
  "type": "Feature",
  "properties": {
    "gn:admin1_code":"14",
    "gn:asciiname":"Gualchua",
    "gn:cc2":"SV",
    "gn:country_code":"SV",
    "gn:dem":30,
    "gn:feature_class":"P",
    "gn:feature_code":"PPL",
    "gn:name":"Gualchua",
    "gn:population":0,
    "gn:timezone":"America/El_Salvador",
    "iso:country":"SV",
    "name:und_x_variant":[
        "Guachua",
        "Gualchua"
    ],
    "wof:name":"Gualchua",
    "wof:placetype":"locality"
},
  "geometry": {"coordinates":[-88.31667,13.26667],"type":"Point"}
}