{
  "type": "Feature",
  "properties": {
    "gn:admin1_code":"02",
    "gn:asciiname":"La Calera",
    "gn:country_code":"SV",
    "gn:dem":209,
    "gn:feature_class":"P",
    "gn:feature_code":"PPL",
    "gn:name":"La Calera",
    "gn:population":0,
    "gn:timezone":"America/El_Salvador",
    "iso:country":"SV",
    "wof:name":"La Calera",
    "wof:placetype":"locality"
},
  "geometry": {"coordinates":[-88.73333000000002,13.95],"type":"Point"}
}