{
  "type": "Feature",
  "properties": {
    "gn:admin1_code":"11",
    "gn:asciiname":"San Jeronimo",
    "gn:cc2":"SV",
    "gn:country_code":"SV",
    "gn:dem":464,
    "gn:feature_class":"P",
    "gn:feature_code":"PPL",
    "gn:name":"San Jer\u00f3nimo",
    "gn:population":0,
    "gn:timezone":"America/El_Salvador",
    "iso:country":"SV",
    "name:und_x_variant":[
        "Caser\u00edo San Jer\u00f3nimo",
        "San Jer\u00f3nimo"
    ],
    "wof:name":"San Jeronimo",
    "wof:placetype":"locality"
},
  "geometry": {"coordinates":[-89.53333000000001,14.38333],"type":"Point"}
}