{
  "type": "Feature",
  "properties": {
    "gn:admin1_code":"11",
    "gn:asciiname":"San Miguelito",
    "gn:cc2":"SV",
    "gn:country_code":"SV",
    "gn:dem":493,
    "gn:feature_class":"P",
    "gn:feature_code":"PPL",
    "gn:name":"San Miguelito",
    "gn:population":0,
    "gn:timezone":"America/El_Salvador",
    "iso:country":"SV",
    "name:und_x_variant":[
        "Caser\u00edo San Miguelito",
        "San Miguelito"
    ],
    "wof:name":"San Miguelito",
    "wof:placetype":"locality"
},
  "geometry": {"coordinates":[-89.44833,13.98583],"type":"Point"}
}