{
  "type": "Feature",
  "properties": {
    "gn:admin1_code":"11",
    "gn:asciiname":"Joya del Maguey",
    "gn:country_code":"SV",
    "gn:dem":461,
    "gn:feature_class":"P",
    "gn:feature_code":"PPL",
    "gn:name":"Joya del Maguey",
    "gn:population":0,
    "gn:timezone":"America/El_Salvador",
    "iso:country":"SV",
    "wof:name":"Joya del Maguey",
    "wof:placetype":"locality"
},
  "geometry": {"coordinates":[-89.28471999999999,13.89167],"type":"Point"}
}