{
  "type": "Feature",
  "properties": {
    "gn:admin1_code":"03",
    "gn:asciiname":"Sumpul de Chacones",
    "gn:cc2":"SV",
    "gn:country_code":"SV",
    "gn:dem":1177,
    "gn:feature_class":"P",
    "gn:feature_code":"PPL",
    "gn:name":"Sumpul de Chacones",
    "gn:population":0,
    "gn:timezone":"America/El_Salvador",
    "iso:country":"SV",
    "name:und_x_variant":[
        "Sumpul",
        "Sumpul Chacones",
        "Sumpul de Chacones"
    ],
    "wof:name":"Sumpul de Chacones",
    "wof:placetype":"locality"
},
  "geometry": {"coordinates":[-89.06667,14.25],"type":"Point"}
}