{
  "type": "Feature",
  "properties": {
    "gn:admin1_code":"10",
    "gn:asciiname":"Palo Grande",
    "gn:country_code":"SV",
    "gn:dem":405,
    "gn:feature_class":"P",
    "gn:feature_code":"PPL",
    "gn:name":"Palo Grande",
    "gn:population":0,
    "gn:timezone":"America/El_Salvador",
    "iso:country":"SV",
    "name:ita_x_preferred":[
        "Palo Grande"
    ],
    "name:spa_x_preferred":[
        "Palo Grande"
    ],
    "name:zho_x_preferred":[
        "\u5e15\u6d1b\u683c\u5170\u5fb7"
    ],
    "wof:name":"Palo Grande",
    "wof:placetype":"locality"
},
  "geometry": {"coordinates":[-89.21889,13.54361],"type":"Point"}
}