{
  "type": "Feature",
  "properties": {
    "gn:admin1_code":"14",
    "gn:asciiname":"El Chapernal",
    "gn:country_code":"SV",
    "gn:dem":32,
    "gn:feature_class":"P",
    "gn:feature_code":"PPL",
    "gn:name":"El Chapernal",
    "gn:population":0,
    "gn:timezone":"America/El_Salvador",
    "iso:country":"SV",
    "wof:name":"El Chapernal",
    "wof:placetype":"locality"
},
  "geometry": {"coordinates":[-88.15000000000001,13.18028],"type":"Point"}
}