{
  "type": "Feature",
  "properties": {
    "gn:admin1_code":"11",
    "gn:asciiname":"Santa Efigenia",
    "gn:country_code":"SV",
    "gn:dem":550,
    "gn:feature_class":"P",
    "gn:feature_code":"PPL",
    "gn:name":"Santa Efigenia",
    "gn:population":0,
    "gn:timezone":"America/El_Salvador",
    "iso:country":"SV",
    "wof:name":"Santa Efigenia",
    "wof:placetype":"locality"
},
  "geometry": {"coordinates":[-89.41249999999999,13.97],"type":"Point"}
}