{
  "type": "Feature",
  "properties": {
    "gn:admin1_code":"7.0",
    "gn:asciiname":"Las Ahogadas",
    "gn:country_code":"SV",
    "gn:dem":12,
    "gn:feature_class":"P",
    "gn:feature_code":"PPL",
    "gn:name":"Las Ahogadas",
    "gn:population":0,
    "gn:timezone":"America/El_Salvador",
    "iso:country":"SV",
    "wof:name":"Las Ahogadas",
    "wof:placetype":"locality"
},
  "geometry": {"coordinates":[-87.67694,13.32722],"type":"Point"}
}