{
  "type": "Feature",
  "properties": {
    "gn:admin1_code":"12",
    "gn:asciiname":"San Felipito",
    "gn:cc2":"SV",
    "gn:country_code":"SV",
    "gn:dem":301,
    "gn:feature_class":"P",
    "gn:feature_code":"PPL",
    "gn:name":"San Felipito",
    "gn:population":0,
    "gn:timezone":"America/El_Salvador",
    "iso:country":"SV",
    "name:und_x_variant":[
        "Caser\u00edo San Felipe",
        "San Felipe",
        "San Felipito"
    ],
    "wof:name":"San Felipito",
    "wof:placetype":"locality"
},
  "geometry": {"coordinates":[-88.68333,13.63333],"type":"Point"}
}