{
  "type": "Feature",
  "properties": {
    "gn:admin1_code":"09",
    "gn:asciiname":"El Jiote",
    "gn:cc2":"SV",
    "gn:country_code":"SV",
    "gn:dem":322,
    "gn:feature_class":"P",
    "gn:feature_code":"PPL",
    "gn:name":"El Jiote",
    "gn:population":0,
    "gn:timezone":"America/El_Salvador",
    "iso:country":"SV",
    "name:und_x_variant":[
        "Caser\u00edo El Jiote",
        "El Jiote"
    ],
    "wof:name":"El Jiote",
    "wof:placetype":"locality"
},
  "geometry": {"coordinates":[-88.25,13.66667],"type":"Point"}
}