{
  "type": "Feature",
  "properties": {
    "gn:admin1_code":"07",
    "gn:asciiname":"Munguia",
    "gn:cc2":"SV",
    "gn:country_code":"SV",
    "gn:dem":181,
    "gn:feature_class":"P",
    "gn:feature_code":"PPL",
    "gn:name":"Mungu\u00eda",
    "gn:population":0,
    "gn:timezone":"America/El_Salvador",
    "iso:country":"SV",
    "name:und_x_variant":[
        "Los Mungu\u00eda",
        "Mungu\u00eda"
    ],
    "wof:name":"Munguia",
    "wof:placetype":"locality"
},
  "geometry": {"coordinates":[-87.78333000000001,13.78333],"type":"Point"}
}