{
  "type": "Feature",
  "properties": {
    "gn:admin1_code":"10",
    "gn:asciiname":"El Jicaron",
    "gn:cc2":"SV",
    "gn:country_code":"SV",
    "gn:dem":402,
    "gn:feature_class":"P",
    "gn:feature_code":"PPL",
    "gn:name":"El Jicar\u00f3n",
    "gn:population":0,
    "gn:timezone":"America/El_Salvador",
    "iso:country":"SV",
    "name:und_x_variant":[
        "Caser\u00edo Jicaron",
        "El Jicar\u00f3n"
    ],
    "wof:name":"El Jicaron",
    "wof:placetype":"locality"
},
  "geometry": {"coordinates":[-89.25528,13.99639],"type":"Point"}
}