{
  "type": "Feature",
  "properties": {
    "gn:admin1_code":"10",
    "gn:asciiname":"Pishishapa",
    "gn:cc2":"SV",
    "gn:country_code":"SV",
    "gn:dem":288,
    "gn:feature_class":"P",
    "gn:feature_code":"PPL",
    "gn:name":"Pishishapa",
    "gn:population":0,
    "gn:timezone":"America/El_Salvador",
    "iso:country":"SV",
    "name:und_x_variant":[
        "Hacienda Pishishapa",
        "Pischishapa",
        "Pishishapa"
    ],
    "wof:name":"Pishishapa",
    "wof:placetype":"locality"
},
  "geometry": {"coordinates":[-89.17471999999999,13.96056],"type":"Point"}
}