{
  "type": "Feature",
  "properties": {
    "gn:admin1_code":"07",
    "gn:asciiname":"El Rebalse",
    "gn:cc2":"SV",
    "gn:country_code":"SV",
    "gn:dem":46,
    "gn:feature_class":"P",
    "gn:feature_code":"PPL",
    "gn:name":"El Rebalse",
    "gn:population":0,
    "gn:timezone":"America/El_Salvador",
    "iso:country":"SV",
    "name:und_x_variant":[
        "Rebolsa",
        "El Rebalse"
    ],
    "wof:name":"El Rebalse",
    "wof:placetype":"locality"
},
  "geometry": {"coordinates":[-87.86694,13.50111],"type":"Point"}
}