{
  "type": "Feature",
  "properties": {
    "gn:admin1_code":"11",
    "gn:asciiname":"Ranchador",
    "gn:cc2":"SV",
    "gn:country_code":"SV",
    "gn:dem":745,
    "gn:feature_class":"P",
    "gn:feature_code":"PPL",
    "gn:name":"Ranchador",
    "gn:population":0,
    "gn:timezone":"America/El_Salvador",
    "iso:country":"SV",
    "name:und_x_variant":[
        "El Ranchador",
        "Ranchador"
    ],
    "wof:name":"Ranchador",
    "wof:placetype":"locality"
},
  "geometry": {"coordinates":[-89.59999999999999,14.01667],"type":"Point"}
}