{
  "type": "Feature",
  "properties": {
    "gn:admin1_code":"10",
    "gn:asciiname":"San Isidro",
    "gn:country_code":"SV",
    "gn:dem":639,
    "gn:feature_class":"P",
    "gn:feature_code":"PPL",
    "gn:name":"San Isidro",
    "gn:population":0,
    "gn:timezone":"America/El_Salvador",
    "iso:country":"SV",
    "wof:name":"San Isidro",
    "wof:placetype":"locality"
},
  "geometry": {"coordinates":[-89.17278,13.58139],"type":"Point"}
}