{
  "type": "Feature",
  "properties": {
    "gn:admin1_code":"05",
    "gn:asciiname":"Ayagualo",
    "gn:country_code":"SV",
    "gn:dem":952,
    "gn:feature_class":"P",
    "gn:feature_code":"PPL",
    "gn:name":"Ayagualo",
    "gn:population":0,
    "gn:timezone":"America/El_Salvador",
    "iso:country":"SV",
    "wof:name":"Ayagualo",
    "wof:placetype":"locality"
},
  "geometry": {"coordinates":[-89.28778,13.6375],"type":"Point"}
}