{
  "type": "Feature",
  "properties": {
    "gn:admin1_code":"08",
    "gn:asciiname":"El Tambor",
    "gn:cc2":"SV",
    "gn:country_code":"SV",
    "gn:dem":492,
    "gn:feature_class":"P",
    "gn:feature_code":"PPL",
    "gn:name":"El Tambor",
    "gn:population":0,
    "gn:timezone":"America/El_Salvador",
    "iso:country":"SV",
    "name:und_x_variant":[
        "Valle El Tambor",
        "El Tambor"
    ],
    "wof:name":"El Tambor",
    "wof:placetype":"locality"
},
  "geometry": {"coordinates":[-88.03333000000001,13.81667],"type":"Point"}
}