{
  "type": "Feature",
  "properties": {
    "gn:admin1_code":"11",
    "gn:asciiname":"Hacienda Santa Rosa",
    "gn:cc2":"SV",
    "gn:country_code":"SV",
    "gn:dem":1110,
    "gn:feature_class":"P",
    "gn:feature_code":"PPL",
    "gn:name":"Hacienda Santa Rosa",
    "gn:population":0,
    "gn:timezone":"America/El_Salvador",
    "iso:country":"SV",
    "name:und_x_variant":[
        "Santa Rosa",
        "Hacienda Santa Rosa"
    ],
    "wof:name":"Hacienda Santa Rosa",
    "wof:placetype":"locality"
},
  "geometry": {"coordinates":[-89.58333,13.86667],"type":"Point"}
}