{
  "type": "Feature",
  "properties": {
    "gn:admin1_code":"10",
    "gn:asciiname":"Consolacion",
    "gn:cc2":"SV",
    "gn:country_code":"SV",
    "gn:dem":409,
    "gn:feature_class":"P",
    "gn:feature_code":"PPL",
    "gn:name":"Consolaci\u00f3n",
    "gn:population":0,
    "gn:timezone":"America/El_Salvador",
    "iso:country":"SV",
    "name:und_x_variant":[
        "Hacienda Consolaci\u00f3n",
        "Consolaci\u00f3n"
    ],
    "wof:name":"Consolacion",
    "wof:placetype":"locality"
},
  "geometry": {"coordinates":[-89.26694000000001,13.98111],"type":"Point"}
}