{
  "type": "Feature",
  "properties": {
    "gn:admin1_code":"07",
    "gn:asciiname":"El Pastor",
    "gn:country_code":"SV",
    "gn:dem":163,
    "gn:feature_class":"P",
    "gn:feature_code":"PPL",
    "gn:name":"El Pastor",
    "gn:population":0,
    "gn:timezone":"America/El_Salvador",
    "iso:country":"SV",
    "wof:name":"El Pastor",
    "wof:placetype":"locality"
},
  "geometry": {"coordinates":[-88.02833000000003,13.45611],"type":"Point"}
}