{
  "type": "Feature",
  "properties": {
    "iso:country":"SV",
    "qs:gn_pop":0,
    "qs:name":"Largo de Coatepeque",
    "qs:name_adm0":"El Salvador",
    "qs:name_adm1":"Santa Ana",
    "qs:photos":411,
    "qs:photos_1k":83,
    "qs:photos_9k":2,
    "qs:photos_9r":5,
    "qs:photos_all":411,
    "qs:photos_sr":6,
    "qs:placetype":"Town",
    "qs:pop_sr":"0",
    "qs:woe_adm0":23424807,
    "wof:name":"Largo de Coatepeque",
    "wof:placetype":"locality"
},
  "geometry": {"coordinates":[-89.542694,13.85008],"type":"Point"}
}