{
  "type": "Feature",
  "properties": {
    "iso:country":"SV",
    "name:ara_x_preferred":[
        "\u062a\u0634\u064a\u0631\u064a\u0644\u0627\u063a\u0648\u0627"
    ],
    "name:ben_x_preferred":[
        "\u099a\u09bf\u09b0\u09bf\u09b2\u09be\u0997\u09cb\u09af\u09bc\u09be"
    ],
    "name:bul_x_preferred":[
        "\u0427\u0438\u0440\u0438\u043b\u0430\u0433\u0443\u0430"
    ],
    "name:chi_x_preferred":[
        "\u5947\u91cc\u62c9\u74dc"
    ],
    "name:dan_x_preferred":[
        "Chirilagua"
    ],
    "name:dut_x_preferred":[
        "Chirilagua"
    ],
    "name:eng_x_preferred":[
        "Chirilagua"
    ],
    "name:fin_x_preferred":[
        "Chirilagua"
    ],
    "name:fre_x_preferred":[
        "Chirilagua"
    ],
    "name:gre_x_preferred":[
        "\u03a4\u03c3\u03b9\u03c1\u03b9\u03bb\u03ac\u03b3\u03ba\u03bf\u03c5\u03b1"
    ],
    "name:guj_x_preferred":[
        "\u0a9a\u0abf\u0ab0\u0ac0\u0ab2\u0a97\u0ac1\u0a86"
    ],
    "name:hin_x_preferred":[
        "\u0915\u093f\u0930\u0940\u0932\u093e\u0917\u0942\u0906"
    ],
    "name:ind_x_preferred":[
        "Chirilagua"
    ],
    "name:ita_x_preferred":[
        "Chirilagua"
    ],
    "name:jpn_x_preferred":[
        "\u30c1\u30ea\u30e9\u30b0\u30a2"
    ],
    "name:kan_x_preferred":[
        "\u0c9a\u0cbf\u0cb0\u0cbf\u0cb2\u0c97\u0cc1\u0cb5\u0cbe"
    ],
    "name:kor_x_preferred":[
        "\uce58\ub9ac\ub77c\uad6c\uc544"
    ],
    "name:lav_x_preferred":[
        "\u010cirilagva"
    ],
    "name:lit_x_preferred":[
        "\u010cirilagva"
    ],
    "name:mar_x_preferred":[
        "\u091a\u093f\u0932\u0940\u0917\u093e\u0917\u0941\u0906"
    ],
    "name:may_x_preferred":[
        "Chirilagua"
    ],
    "name:nob_x_preferred":[
        "Chirilagua"
    ],
    "name:pol_x_preferred":[
        "Chirilagua"
    ],
    "name:por_x_preferred":[
        "Chirilagua"
    ],
    "name:rus_x_preferred":[
        "\u0427\u0438\u0440\u0438\u043b\u0430\u0433\u0443\u0430"
    ],
    "name:sin_x_preferred":[
        "\u0da0\u0dd2\u0dbb\u0dd2\u0dbd\u0d9c\u0dd4\u0dc0\u0dcf"
    ],
    "name:spa_x_preferred":[
        "Chirilagua"
    ],
    "name:swe_x_preferred":[
        "Chirilagua"
    ],
    "name:tam_x_preferred":[
        "\u0ba8\u0bcb\u0bb5\u0bbf  \u0baf\u0bc2\u0bb0\u0bc6\u0b99\u0bcd\u0b95\u0bcb\u0baf\u0bcd"
    ],
    "name:tel_x_preferred":[
        "\u0c1a\u0c3f\u0c30\u0c3f\u0c32\u0c3e\u0c17\u0c4d\u0c35\u0c3e"
    ],
    "name:tha_x_preferred":[
        "\u0e34\u0e23\u0e34\u0e23\u0e32\u0e01\u0e31\u0e27"
    ],
    "name:tur_x_preferred":[
        "Chiralagua"
    ],
    "name:ukr_x_preferred":[
        "\u0427\u0456\u0440\u0456\u043b\u0430\u0443\u0433\u0430"
    ],
    "name:urd_x_preferred":[
        "\u0686\u06cc\u0631\u06cc\u0644\u0627\u062c\u0648\u0627"
    ],
    "name:vie_x_preferred":[
        "Chirilagua"
    ],
    "name:zho_x_preferred":[
        "\u5947\u91cc\u62c9\u74dc"
    ],
    "qs:gn_country":"SV",
    "qs:gn_fcode":"PPL",
    "qs:gn_pop":6393,
    "qs:name":"Chirilagua",
    "qs:name_adm0":"El Salvador",
    "qs:name_adm1":"San Miguel",
    "qs:photos":49,
    "qs:photos_1k":10,
    "qs:photos_9k":1,
    "qs:photos_9r":2,
    "qs:photos_all":49,
    "qs:photos_sr":2,
    "qs:placetype":"Town",
    "qs:pop_sr":"5",
    "qs:woe_adm0":23424807,
    "wof:name":"Chirilagua",
    "wof:placetype":"locality",
    "wof:population":6393
},
  "geometry": {"coordinates":[-88.13861,13.22028],"type":"Point"}
}