{
  "type": "Feature",
  "properties": {
    "gn:admin1_code":"06",
    "gn:asciiname":"El Tapechame",
    "gn:cc2":"SV",
    "gn:country_code":"SV",
    "gn:dem":319,
    "gn:feature_class":"P",
    "gn:feature_code":"PPL",
    "gn:name":"El Tapechame",
    "gn:population":0,
    "gn:timezone":"America/El_Salvador",
    "iso:country":"SV",
    "name:und_x_variant":[
        "Tepechama",
        "El Tapechame"
    ],
    "wof:name":"El Tapechame",
    "wof:placetype":"locality"
},
  "geometry": {"coordinates":[-88.88333,13.53333],"type":"Point"}
}