{
  "type": "Feature",
  "properties": {
    "gn:admin1_code":"03",
    "gn:asciiname":"Hacienda Los Jobos",
    "gn:cc2":"SV",
    "gn:country_code":"SV",
    "gn:dem":312,
    "gn:feature_class":"P",
    "gn:feature_code":"PPL",
    "gn:name":"Hacienda Los Jobos",
    "gn:population":0,
    "gn:timezone":"America/El_Salvador",
    "iso:country":"SV",
    "name:und_x_variant":[
        "Los Jobos",
        "Hacienda Los Jobos"
    ],
    "wof:name":"Hacienda Los Jobos",
    "wof:placetype":"locality"
},
  "geometry": {"coordinates":[-89.41667,14.08333],"type":"Point"}
}