{
  "type": "Feature",
  "properties": {
    "gn:admin1_code":"9.0",
    "gn:asciiname":"Valle Nuevo",
    "gn:country_code":"SV",
    "gn:dem":106,
    "gn:feature_class":"P",
    "gn:feature_code":"PPL",
    "gn:name":"Valle Nuevo",
    "gn:population":0,
    "gn:timezone":"America/El_Salvador",
    "iso:country":"SV",
    "wof:name":"Valle Nuevo",
    "wof:placetype":"locality"
},
  "geometry": {"coordinates":[-88.10250000000001,13.44222],"type":"Point"}
}