{
  "type": "Feature",
  "properties": {
    "gn:admin1_code":"10",
    "gn:asciiname":"Plan del Mango",
    "gn:country_code":"SV",
    "gn:dem":134,
    "gn:feature_class":"P",
    "gn:feature_code":"PPL",
    "gn:name":"Plan del Mango",
    "gn:population":0,
    "gn:timezone":"America/El_Salvador",
    "iso:country":"SV",
    "wof:name":"Plan del Mango",
    "wof:placetype":"locality"
},
  "geometry": {"coordinates":[-89.19778000000002,13.50639],"type":"Point"}
}