{
  "type": "Feature",
  "properties": {
    "gn:admin1_code":"07",
    "gn:asciiname":"Llano El Irire",
    "gn:country_code":"SV",
    "gn:dem":68,
    "gn:feature_class":"P",
    "gn:feature_code":"PPL",
    "gn:name":"Llano El Irire",
    "gn:population":0,
    "gn:timezone":"America/El_Salvador",
    "iso:country":"SV",
    "wof:name":"Llano El Irire",
    "wof:placetype":"locality"
},
  "geometry": {"coordinates":[-87.76666999999998,13.63333],"type":"Point"}
}