{
  "type": "Feature",
  "properties": {
    "gn:admin1_code":"07",
    "gn:asciiname":"La Barahona",
    "gn:cc2":"SV",
    "gn:country_code":"SV",
    "gn:dem":152,
    "gn:feature_class":"P",
    "gn:feature_code":"PPL",
    "gn:name":"La Barahona",
    "gn:population":0,
    "gn:timezone":"America/El_Salvador",
    "iso:country":"SV",
    "name:und_x_variant":[
        "Barahona",
        "La Barahona"
    ],
    "wof:name":"La Barahona",
    "wof:placetype":"locality"
},
  "geometry": {"coordinates":[-87.91667,13.46667],"type":"Point"}
}