{
  "type": "Feature",
  "properties": {
    "gn:admin1_code":"05",
    "gn:asciiname":"Sihuapilapa",
    "gn:cc2":"SV",
    "gn:country_code":"SV",
    "gn:dem":336,
    "gn:feature_class":"P",
    "gn:feature_code":"PPL",
    "gn:name":"Sihuapilapa",
    "gn:population":0,
    "gn:timezone":"America/El_Salvador",
    "iso:country":"SV",
    "name:und_x_variant":[
        "Suhuapilapa",
        "Siguapilapa",
        "Sihuapilapa"
    ],
    "wof:name":"Sihuapilapa",
    "wof:placetype":"locality"
},
  "geometry": {"coordinates":[-89.56667,13.56667],"type":"Point"}
}