{
  "type": "Feature",
  "properties": {
    "gn:admin1_code":"12",
    "gn:asciiname":"El Pedregal",
    "gn:cc2":"SV",
    "gn:country_code":"SV",
    "gn:dem":24,
    "gn:feature_class":"P",
    "gn:feature_code":"PPL",
    "gn:name":"El Pedregal",
    "gn:population":0,
    "gn:timezone":"America/El_Salvador",
    "iso:country":"SV",
    "name:und_x_variant":[
        "Caser\u00edo Pedregal",
        "El Pedregal"
    ],
    "wof:name":"El Pedregal",
    "wof:placetype":"locality"
},
  "geometry": {"coordinates":[-88.65000000000001,13.58333],"type":"Point"}
}