{
  "type": "Feature",
  "properties": {
    "gn:admin1_code":"04",
    "gn:asciiname":"Tecomatepeque",
    "gn:cc2":"SV",
    "gn:country_code":"SV",
    "gn:dem":623,
    "gn:feature_class":"P",
    "gn:feature_code":"PPL",
    "gn:name":"Tecomatepeque",
    "gn:population":0,
    "gn:timezone":"America/El_Salvador",
    "iso:country":"SV",
    "name:und_x_variant":[
        "Tecomatepe",
        "Tecomatepeque"
    ],
    "wof:name":"Tecomatepeque",
    "wof:placetype":"locality"
},
  "geometry": {"coordinates":[-89.03389,13.84139],"type":"Point"}
}