{
  "type": "Feature",
  "properties": {
    "gn:admin1_code":"13.0",
    "gn:asciiname":"Rio Las Monjas",
    "gn:country_code":"SV",
    "gn:dem":747,
    "gn:feature_class":"P",
    "gn:feature_code":"PPL",
    "gn:name":"R\u00edo Las Monjas",
    "gn:population":0,
    "gn:timezone":"America/El_Salvador",
    "iso:country":"SV",
    "wof:name":"Rio Las Monjas",
    "wof:placetype":"locality"
},
  "geometry": {"coordinates":[-89.71083,13.81333],"type":"Point"}
}