{
  "type": "Feature",
  "properties": {
    "gn:admin1_code":"11",
    "gn:asciiname":"Chimalapa",
    "gn:cc2":"SV",
    "gn:country_code":"SV",
    "gn:dem":505,
    "gn:feature_class":"P",
    "gn:feature_code":"PPL",
    "gn:name":"Chimalapa",
    "gn:population":0,
    "gn:timezone":"America/El_Salvador",
    "iso:country":"SV",
    "name:und_x_variant":[
        "Simalapa",
        "Caser\u00edo Chimalapa",
        "Chimalapa"
    ],
    "wof:name":"Chimalapa",
    "wof:placetype":"locality"
},
  "geometry": {"coordinates":[-89.45,14.35],"type":"Point"}
}