{
  "type": "Feature",
  "properties": {
    "gn:admin1_code":"11",
    "gn:asciiname":"Palo Galan",
    "gn:country_code":"SV",
    "gn:dem":471,
    "gn:feature_class":"P",
    "gn:feature_code":"PPL",
    "gn:name":"Palo Gal\u00e1n",
    "gn:population":0,
    "gn:timezone":"America/El_Salvador",
    "iso:country":"SV",
    "wof:name":"Palo Galan",
    "wof:placetype":"locality"
},
  "geometry": {"coordinates":[-89.33333,14.21667],"type":"Point"}
}