{
  "type": "Feature",
  "properties": {
    "gn:admin1_code":"14",
    "gn:asciiname":"Hacienda La Hulera",
    "gn:cc2":"SV",
    "gn:country_code":"SV",
    "gn:dem":167,
    "gn:feature_class":"P",
    "gn:feature_code":"PPL",
    "gn:name":"Hacienda La Hulera",
    "gn:population":0,
    "gn:timezone":"America/El_Salvador",
    "iso:country":"SV",
    "name:und_x_variant":[
        "La Hulera",
        "Hacienda La Hulera"
    ],
    "wof:name":"Hacienda La Hulera",
    "wof:placetype":"locality"
},
  "geometry": {"coordinates":[-88.48333000000002,13.36667],"type":"Point"}
}