{
  "type": "Feature",
  "properties": {
    "gn:admin1_code":"12",
    "gn:asciiname":"El Coyolar",
    "gn:cc2":"SV",
    "gn:country_code":"SV",
    "gn:dem":473,
    "gn:feature_class":"P",
    "gn:feature_code":"PPL",
    "gn:name":"El Coyolar",
    "gn:population":0,
    "gn:timezone":"America/El_Salvador",
    "iso:country":"SV",
    "name:und_x_variant":[
        "Caser\u00edo El Coyolar",
        "El Coyolar"
    ],
    "wof:name":"El Coyolar",
    "wof:placetype":"locality"
},
  "geometry": {"coordinates":[-88.61667,13.61667],"type":"Point"}
}