{
  "type": "Feature",
  "properties": {
    "gn:admin1_code":"09",
    "gn:asciiname":"Santo Tomas",
    "gn:country_code":"SV",
    "gn:dem":183,
    "gn:feature_class":"P",
    "gn:feature_code":"PPL",
    "gn:name":"Santo Tom\u00e1s",
    "gn:population":0,
    "gn:timezone":"America/El_Salvador",
    "iso:country":"SV",
    "name:ceb_x_preferred":[
        "Santo Tomas"
    ],
    "name:deu_x_preferred":[
        "Santo Tomas"
    ],
    "name:ilo_x_preferred":[
        "Santo Tomas"
    ],
    "name:lit_x_preferred":[
        "Santo Tomas"
    ],
    "name:nld_x_preferred":[
        "Santo Tomas"
    ],
    "name:sco_x_preferred":[
        "Santo Tomas"
    ],
    "name:srp_x_preferred":[
        "\u0421\u0430\u043d\u0442\u043e \u0422\u043e\u043c\u0430\u0441"
    ],
    "name:swe_x_preferred":[
        "Santo Tomas"
    ],
    "name:war_x_preferred":[
        "Santo Tomas"
    ],
    "wof:name":"Santo Tomas",
    "wof:placetype":"locality"
},
  "geometry": {"coordinates":[-88.28333000000001,13.63333],"type":"Point"}
}