{
  "type": "Feature",
  "properties": {
    "gn:admin1_code":"07",
    "gn:asciiname":"Concepcion de Oriente",
    "gn:cc2":"SV",
    "gn:country_code":"SV",
    "gn:dem":145,
    "gn:feature_class":"P",
    "gn:feature_code":"PPL",
    "gn:name":"Concepci\u00f3n de Oriente",
    "gn:population":0,
    "gn:timezone":"America/El_Salvador",
    "iso:country":"SV",
    "name:und_x_variant":[
        "Nueva Concepcion Oriente",
        "Nueva Concepci\u00f3n de Oriente",
        "Concepci\u00f3n de Oriente"
    ],
    "name:zho_x_preferred":[
        "\u5eb7\u585e\u666e\u897f\u7fc1\u5fb7\u5967\u9023\u7279"
    ],
    "wof:name":"Concepcion de Oriente",
    "wof:placetype":"locality"
},
  "geometry": {"coordinates":[-87.71666999999999,13.79139],"type":"Point"}
}