{
  "type": "Feature",
  "properties": {
    "gn:admin1_code":"09",
    "gn:asciiname":"San Antonio Silva",
    "gn:cc2":"SV",
    "gn:country_code":"SV",
    "gn:dem":92,
    "gn:feature_class":"P",
    "gn:feature_code":"PPL",
    "gn:name":"San Antonio Silva",
    "gn:population":0,
    "gn:timezone":"America/El_Salvador",
    "iso:country":"SV",
    "name:und_x_variant":[
        "Caser\u00edo San Antonio Silva",
        "San Antonio de Silva",
        "San Antonio Silva"
    ],
    "wof:name":"San Antonio Silva",
    "wof:placetype":"locality"
},
  "geometry": {"coordinates":[-88.03028,13.39389],"type":"Point"}
}