{
  "type": "Feature",
  "properties": {
    "gn:admin1_code":"11.0",
    "gn:asciiname":"Caserio Las Conchas",
    "gn:cc2":"SV",
    "gn:country_code":"SV",
    "gn:dem":445,
    "gn:feature_class":"P",
    "gn:feature_code":"PPL",
    "gn:name":"Caser\u00edo Las Conchas",
    "gn:population":0,
    "gn:timezone":"America/El_Salvador",
    "iso:country":"SV",
    "name:und_x_variant":[
        "Las Conchas",
        "Caser\u00edo Las Conchas"
    ],
    "wof:name":"Caserio Las Conchas",
    "wof:placetype":"locality"
},
  "geometry": {"coordinates":[-89.51528,14.30556],"type":"Point"}
}