{
  "type": "Feature",
  "properties": {
    "gn:admin1_code":"14",
    "gn:asciiname":"Joya Ancha Arriba",
    "gn:country_code":"SV",
    "gn:dem":298,
    "gn:feature_class":"P",
    "gn:feature_code":"PPL",
    "gn:name":"Joya Ancha Arriba",
    "gn:population":0,
    "gn:timezone":"America/El_Salvador",
    "iso:country":"SV",
    "wof:name":"Joya Ancha Arriba",
    "wof:placetype":"locality"
},
  "geometry": {"coordinates":[-88.40000000000001,13.41667],"type":"Point"}
}