{
  "type": "Feature",
  "properties": {
    "gn:admin1_code":"08",
    "gn:asciiname":"Las Conchas",
    "gn:country_code":"SV",
    "gn:dem":193,
    "gn:feature_class":"P",
    "gn:feature_code":"PPL",
    "gn:name":"Las Conchas",
    "gn:population":0,
    "gn:timezone":"America/El_Salvador",
    "iso:country":"SV",
    "wof:name":"Las Conchas",
    "wof:placetype":"locality"
},
  "geometry": {"coordinates":[-88.08333,13.56667],"type":"Point"}
}