{
  "type": "Feature",
  "properties": {
    "gn:admin1_code":"14",
    "gn:asciiname":"La Constancia",
    "gn:cc2":"SV",
    "gn:country_code":"SV",
    "gn:dem":103,
    "gn:feature_class":"P",
    "gn:feature_code":"PPL",
    "gn:name":"La Constancia",
    "gn:population":0,
    "gn:timezone":"America/El_Salvador",
    "iso:country":"SV",
    "name:und_x_variant":[
        "La Costanera",
        "La Constancia"
    ],
    "wof:name":"La Constancia",
    "wof:placetype":"locality"
},
  "geometry": {"coordinates":[-88.41667,13.35],"type":"Point"}
}