{
  "type": "Feature",
  "properties": {
    "gn:admin1_code":"05",
    "gn:asciiname":"El Castillo",
    "gn:country_code":"SV",
    "gn:dem":916,
    "gn:feature_class":"P",
    "gn:feature_code":"PPL",
    "gn:name":"El Castillo",
    "gn:population":0,
    "gn:timezone":"America/El_Salvador",
    "iso:country":"SV",
    "name:ceb_x_preferred":[
        "El Castillo"
    ],
    "name:deu_x_preferred":[
        "El Castillo"
    ],
    "name:ita_x_preferred":[
        "El Castillo"
    ],
    "name:nld_x_preferred":[
        "El Castillo"
    ],
    "name:pol_x_preferred":[
        "El Castillo"
    ],
    "name:spa_x_preferred":[
        "El Castillo"
    ],
    "name:swe_x_preferred":[
        "El Castillo"
    ],
    "name:vie_x_preferred":[
        "El Castillo"
    ],
    "wof:name":"El Castillo",
    "wof:placetype":"locality"
},
  "geometry": {"coordinates":[-89.43971999999999,13.91111],"type":"Point"}
}