{
  "type": "Feature",
  "properties": {
    "gn:admin1_code":"06",
    "gn:asciiname":"El Golfo",
    "gn:country_code":"SV",
    "gn:dem":29,
    "gn:feature_class":"P",
    "gn:feature_code":"PPL",
    "gn:name":"El Golfo",
    "gn:population":0,
    "gn:timezone":"America/El_Salvador",
    "iso:country":"SV",
    "wof:name":"El Golfo",
    "wof:placetype":"locality"
},
  "geometry": {"coordinates":[-88.91667,13.43333],"type":"Point"}
}