{
  "type": "Feature",
  "properties": {
    "gn:admin1_code":"13.0",
    "gn:asciiname":"Isla del Cerro",
    "gn:country_code":"SV",
    "gn:dem":844,
    "gn:feature_class":"P",
    "gn:feature_code":"PPL",
    "gn:name":"Isla del Cerro",
    "gn:population":0,
    "gn:timezone":"America/El_Salvador",
    "iso:country":"SV",
    "wof:name":"Isla del Cerro",
    "wof:placetype":"locality"
},
  "geometry": {"coordinates":[-89.56028000000001,13.84278],"type":"Point"}
}