{
  "type": "Feature",
  "properties": {
    "gn:admin1_code":"08",
    "gn:asciiname":"El Rincon",
    "gn:cc2":"SV",
    "gn:country_code":"SV",
    "gn:dem":637,
    "gn:feature_class":"P",
    "gn:feature_code":"PPL",
    "gn:name":"El Rinc\u00f3n",
    "gn:population":0,
    "gn:timezone":"America/El_Salvador",
    "iso:country":"SV",
    "name:und_x_variant":[
        "Jocoaitique",
        "El Rinc\u00f3n"
    ],
    "wof:name":"El Rincon",
    "wof:placetype":"locality"
},
  "geometry": {"coordinates":[-88.13333,13.88333],"type":"Point"}
}