{
  "type": "Feature",
  "properties": {
    "gn:country":"SV",
    "gn:fcode":"PPLX",
    "gn:population":0,
    "iso:country":"SV",
    "name:spa_x_preferred":[
        "Delicias del Norte"
    ],
    "qs_pg:aaroncc":"SV",
    "qs_pg:gn_country":"SV",
    "qs_pg:gn_fcode":"PPLX",
    "qs_pg:gn_pop":0,
    "qs_pg:name":"Delicias del Norte",
    "qs_pg:name_adm0":"El Salvador",
    "qs_pg:name_adm1":"San Salvador",
    "qs_pg:photos":339,
    "qs_pg:photos_1k":69,
    "qs_pg:photos_9k":2,
    "qs_pg:photos_9r":5,
    "qs_pg:photos_all":339,
    "qs_pg:photos_sr":5,
    "qs_pg:pop_sr":0,
    "qs_pg:qs_pg_placetype":"neighbourhood",
    "qs_pg:qs_pg_placetype_gp":"Suburb",
    "qs_pg:woe_adm0":23424807,
    "woe:adm0_id":23424807,
    "woe:name_adm0":"El Salvador",
    "woe:name_adm1":"San Salvador",
    "woe:placetype":"Suburb",
    "wof:name":"Delicias del Norte",
    "wof:placetype":"neighbourhood"
},
  "geometry": {"coordinates":[-89.21666999999999,13.73333],"type":"Point"}
}