{
  "type": "Feature",
  "properties": {
    "gn:admin1_code":"09",
    "gn:asciiname":"Hacienda San Jose",
    "gn:country_code":"SV",
    "gn:dem":43,
    "gn:feature_class":"P",
    "gn:feature_code":"PPL",
    "gn:name":"Hacienda San Jos\u00e9",
    "gn:population":0,
    "gn:timezone":"America/El_Salvador",
    "iso:country":"SV",
    "wof:name":"Hacienda San Jose",
    "wof:placetype":"locality"
},
  "geometry": {"coordinates":[-88.18639,13.30861],"type":"Point"}
}