{
  "type": "Feature",
  "properties": {
    "gn:admin1_code":"09",
    "gn:asciiname":"La Suncuya",
    "gn:country_code":"SV",
    "gn:dem":140,
    "gn:feature_class":"P",
    "gn:feature_code":"PPL",
    "gn:name":"La Suncuya",
    "gn:population":0,
    "gn:timezone":"America/El_Salvador",
    "iso:country":"SV",
    "wof:name":"La Suncuya",
    "wof:placetype":"locality"
},
  "geometry": {"coordinates":[-88.10944000000001,13.22389],"type":"Point"}
}