{
  "type": "Feature",
  "properties": {
    "gn:admin1_code":"01",
    "gn:asciiname":"San Miguelito",
    "gn:country_code":"SV",
    "gn:dem":588,
    "gn:feature_class":"P",
    "gn:feature_code":"PPL",
    "gn:name":"San Miguelito",
    "gn:population":0,
    "gn:timezone":"America/El_Salvador",
    "iso:country":"SV",
    "name:ceb_x_preferred":[
        "San Miguelito"
    ],
    "name:deu_x_preferred":[
        "San Miguelito"
    ],
    "name:ita_x_preferred":[
        "San Miguelito"
    ],
    "name:nld_x_preferred":[
        "San Miguelito"
    ],
    "name:pol_x_preferred":[
        "San Miguelito"
    ],
    "name:spa_x_preferred":[
        "San Miguelito"
    ],
    "name:swe_x_preferred":[
        "San Miguelito"
    ],
    "wof:name":"San Miguelito",
    "wof:placetype":"locality"
},
  "geometry": {"coordinates":[-89.95,13.81667],"type":"Point"}
}