{
  "type": "Feature",
  "properties": {
    "gn:admin1_code":"14",
    "gn:asciiname":"Hacienda San Mariano",
    "gn:country_code":"SV",
    "gn:dem":565,
    "gn:feature_class":"P",
    "gn:feature_code":"PPL",
    "gn:name":"Hacienda San Mariano",
    "gn:population":0,
    "gn:timezone":"America/El_Salvador",
    "iso:country":"SV",
    "wof:name":"Hacienda San Mariano",
    "wof:placetype":"locality"
},
  "geometry": {"coordinates":[-88.45,13.41667],"type":"Point"}
}