{
  "type": "Feature",
  "properties": {
    "gn:admin1_code":"09",
    "gn:asciiname":"El Jicaro",
    "gn:country_code":"SV",
    "gn:dem":314,
    "gn:feature_class":"P",
    "gn:feature_code":"PPL",
    "gn:name":"El J\u00edcaro",
    "gn:population":0,
    "gn:timezone":"America/El_Salvador",
    "iso:country":"SV",
    "wof:name":"El Jicaro",
    "wof:placetype":"locality"
},
  "geometry": {"coordinates":[-88.38333,13.58333],"type":"Point"}
}