{
  "type": "Feature",
  "properties": {
    "iso:country":"SV",
    "name:cat_x_preferred":[
        "Metapan"
    ],
    "name:ceb_x_preferred":[
        "Metap\u00e1n"
    ],
    "name:eng_x_preferred":[
        "Metap\u00e1n"
    ],
    "name:eus_x_preferred":[
        "Metap\u00e1n"
    ],
    "name:fra_x_preferred":[
        "Metap\u00e1n"
    ],
    "name:ita_x_preferred":[
        "Metap\u00e1n"
    ],
    "name:jpn_x_preferred":[
        "\u30e1\u30bf\u30d1\u30f3"
    ],
    "name:nah_x_preferred":[
        "Metlapan"
    ],
    "name:nan_x_preferred":[
        "Metap\u00e1n"
    ],
    "name:nld_x_preferred":[
        "Metap\u00e1n"
    ],
    "name:pol_x_preferred":[
        "Metap\u00e1n"
    ],
    "name:por_x_preferred":[
        "Metap\u00e1n"
    ],
    "name:rus_x_preferred":[
        "\u041c\u0435\u0442\u0430\u043f\u0430\u043d"
    ],
    "name:spa_x_preferred":[
        "Metap\u00e1n"
    ],
    "name:srp_x_preferred":[
        "\u041c\u0435\u0442\u0430\u043f\u0430\u043d"
    ],
    "name:urd_x_preferred":[
        "\u0645\u06cc\u062a\u0627\u067e\u0627\u0646"
    ],
    "name:zho_x_preferred":[
        "\u6885\u5854\u6f58"
    ],
    "qs:gn_country":"SV",
    "qs:gn_fcode":"PPL",
    "qs:gn_pop":19143,
    "qs:name":"Metap\u00e1n",
    "qs:name_adm0":"El Salvador",
    "qs:name_adm1":"Santa Ana",
    "qs:photos":71,
    "qs:photos_1k":14,
    "qs:photos_9k":1,
    "qs:photos_9r":2,
    "qs:photos_all":71,
    "qs:photos_sr":2,
    "qs:placetype":"Town",
    "qs:pop_sr":"6",
    "qs:woe_adm0":23424807,
    "wof:name":"Metap\u00e1n",
    "wof:placetype":"locality",
    "wof:population":19143
},
  "geometry": {"coordinates":[-89.45,14.33333],"type":"Point"}
}