{
  "type": "Feature",
  "properties": {
    "gn:admin1_code":"12",
    "gn:asciiname":"Molineros",
    "gn:country_code":"SV",
    "gn:dem":606,
    "gn:feature_class":"P",
    "gn:feature_code":"PPL",
    "gn:name":"Molineros",
    "gn:population":0,
    "gn:timezone":"America/El_Salvador",
    "iso:country":"SV",
    "wof:name":"Molineros",
    "wof:placetype":"locality"
},
  "geometry": {"coordinates":[-88.86667,13.65],"type":"Point"}
}