{
  "type": "Feature",
  "properties": {
    "gn:admin1_code":"13",
    "gn:asciiname":"Cruz Grande",
    "gn:cc2":"SV",
    "gn:country_code":"SV",
    "gn:dem":529,
    "gn:feature_class":"P",
    "gn:feature_code":"PPL",
    "gn:name":"Cruz Grande",
    "gn:population":0,
    "gn:timezone":"America/El_Salvador",
    "iso:country":"SV",
    "name:sco_x_preferred":[
        "Cruz Grande"
    ],
    "name:spa_x_preferred":[
        "Cruz Grande"
    ],
    "name:srp_x_preferred":[
        "\u041a\u0440\u0443\u0437 \u0413\u0440\u0430\u043d\u0434\u0435"
    ],
    "name:und_x_variant":[
        "La Cruz Grande"
    ],
    "wof:name":"Cruz Grande",
    "wof:placetype":"locality"
},
  "geometry": {"coordinates":[-89.66667,13.76667],"type":"Point"}
}