{
  "type": "Feature",
  "properties": {
    "gn:admin1_code":"08",
    "gn:asciiname":"San Juan",
    "gn:cc2":"SV",
    "gn:country_code":"SV",
    "gn:dem":194,
    "gn:feature_class":"P",
    "gn:feature_code":"PPL",
    "gn:name":"San Juan",
    "gn:population":0,
    "gn:timezone":"America/El_Salvador",
    "iso:country":"SV",
    "name:und_x_variant":[
        "San Juan de la Cruz",
        "San Juan"
    ],
    "wof:name":"San Juan",
    "wof:placetype":"locality"
},
  "geometry": {"coordinates":[-88.16667,13.63333],"type":"Point"}
}