{
  "type": "Feature",
  "properties": {
    "gn:admin1_code":"11",
    "gn:asciiname":"La Ceibita",
    "gn:cc2":"SV",
    "gn:country_code":"SV",
    "gn:dem":714,
    "gn:feature_class":"P",
    "gn:feature_code":"PPL",
    "gn:name":"La Ceibita",
    "gn:population":0,
    "gn:timezone":"America/El_Salvador",
    "iso:country":"SV",
    "name:und_x_variant":[
        "Caser\u00edo La Ceibita",
        "Ceibita",
        "La Ceibita"
    ],
    "wof:name":"La Ceibita",
    "wof:placetype":"locality"
},
  "geometry": {"coordinates":[-89.34999999999999,14.26667],"type":"Point"}
}