{
  "type": "Feature",
  "properties": {
    "gn:admin1_code":"7.0",
    "gn:asciiname":"Las Cruces",
    "gn:cc2":"SV",
    "gn:country_code":"SV",
    "gn:dem":326,
    "gn:feature_class":"P",
    "gn:feature_code":"PPL",
    "gn:name":"Las Cruces",
    "gn:population":0,
    "gn:timezone":"America/El_Salvador",
    "iso:country":"SV",
    "name:und_x_variant":[
        "Plan de La Mesa",
        "Las Cruces"
    ],
    "wof:name":"Las Cruces",
    "wof:placetype":"locality"
},
  "geometry": {"coordinates":[-87.99194,13.5425],"type":"Point"}
}