{
  "type": "Feature",
  "properties": {
    "iso:country":"SV",
    "name:deu_x_preferred":[
        "Puerto El Triunfo"
    ],
    "name:eng_x_preferred":[
        "Puerto El Triunfo"
    ],
    "name:fra_x_preferred":[
        "Puerto El Triunfo"
    ],
    "name:ita_x_preferred":[
        "Puerto El Triunfo"
    ],
    "name:jpn_x_preferred":[
        "\u30d7\u30a8\u30eb\u30c8\u30fb\u30a8\u30eb\u30fb\u30c8\u30ea\u30a6\u30f3\u30d5\u30a9"
    ],
    "name:nld_x_preferred":[
        "Puerto El Triunfo"
    ],
    "name:pol_x_preferred":[
        "Puerto El Triunfo"
    ],
    "name:por_x_preferred":[
        "Puerto El Triunfo"
    ],
    "name:spa_x_preferred":[
        "Puerto El Triunfo"
    ],
    "name:unk_x_variant":[
        "Puerto Del Triunfo"
    ],
    "name:zho_x_preferred":[
        "\u57c3\u723e\u7279\u91cc\u6eab\u798f\u6e2f"
    ],
    "qs:gn_country":"SV",
    "qs:gn_fcode":"PPL",
    "qs:gn_pop":19074,
    "qs:name":"Puerto El Triunfo",
    "qs:name_adm0":"El Salvador",
    "qs:name_adm1":"Usulut\u00e1n",
    "qs:photos":115,
    "qs:photos_1k":23,
    "qs:photos_9k":1,
    "qs:photos_9r":3,
    "qs:photos_all":115,
    "qs:photos_sr":3,
    "qs:placetype":"Town",
    "qs:pop_sr":"6",
    "qs:woe_adm0":23424807,
    "wd:wordcount":109,
    "wof:name":"Puerto El Triunfo",
    "wof:placetype":"locality",
    "wof:population":19074
},
  "geometry": {"coordinates":[-88.55,13.28333],"type":"Point"}
}