{
  "type": "Feature",
  "properties": {
    "gn:admin1_code":"09",
    "gn:asciiname":"Hacienda Casa Mota",
    "gn:country_code":"SV",
    "gn:dem":41,
    "gn:feature_class":"P",
    "gn:feature_code":"PPL",
    "gn:name":"Hacienda Casa Mota",
    "gn:population":0,
    "gn:timezone":"America/El_Salvador",
    "iso:country":"SV",
    "wof:name":"Hacienda Casa Mota",
    "wof:placetype":"locality"
},
  "geometry": {"coordinates":[-88.21110999999998,13.325],"type":"Point"}
}