{
  "type": "Feature",
  "properties": {
    "gn:admin1_code":"06",
    "gn:asciiname":"Las Animas",
    "gn:cc2":"SV",
    "gn:country_code":"SV",
    "gn:dem":387,
    "gn:feature_class":"P",
    "gn:feature_code":"PPL",
    "gn:name":"Las \u00c1nimas",
    "gn:population":0,
    "gn:timezone":"America/El_Salvador",
    "iso:country":"SV",
    "name:ceb_x_preferred":[
        "Las Animas"
    ],
    "name:deu_x_preferred":[
        "Las \u00c1nimas"
    ],
    "name:nld_x_preferred":[
        "Las Animas"
    ],
    "name:pol_x_preferred":[
        "Las Animas"
    ],
    "name:spa_x_preferred":[
        "Las \u00c1nimas"
    ],
    "name:srp_x_preferred":[
        "\u041b\u0430\u0441 \u0410\u043d\u0438\u043c\u0430\u0441"
    ],
    "name:swe_x_preferred":[
        "Las Animas"
    ],
    "name:und_x_variant":[
        "\u00c1nimas"
    ],
    "wof:name":"Las Animas",
    "wof:placetype":"locality"
},
  "geometry": {"coordinates":[-88.93333,13.55],"type":"Point"}
}