{
  "type": "Feature",
  "properties": {
    "gn:admin1_code":"14",
    "gn:asciiname":"El Carmelo",
    "gn:country_code":"SV",
    "gn:dem":580,
    "gn:feature_class":"P",
    "gn:feature_code":"PPL",
    "gn:name":"El Carmelo",
    "gn:population":0,
    "gn:timezone":"America/El_Salvador",
    "iso:country":"SV",
    "wof:name":"El Carmelo",
    "wof:placetype":"locality"
},
  "geometry": {"coordinates":[-88.24306,13.26194],"type":"Point"}
}