{
  "type": "Feature",
  "properties": {
    "gn:admin1_code":"09",
    "gn:asciiname":"El Salamar",
    "gn:country_code":"SV",
    "gn:dem":352,
    "gn:feature_class":"P",
    "gn:feature_code":"PPL",
    "gn:name":"El Salamar",
    "gn:population":0,
    "gn:timezone":"America/El_Salvador",
    "iso:country":"SV",
    "wof:name":"El Salamar",
    "wof:placetype":"locality"
},
  "geometry": {"coordinates":[-88.07472,13.49083],"type":"Point"}
}