{
  "type": "Feature",
  "properties": {
    "gn:admin1_code":"09",
    "gn:asciiname":"Hacienda Tongolona",
    "gn:cc2":"SV",
    "gn:country_code":"SV",
    "gn:dem":169,
    "gn:feature_class":"P",
    "gn:feature_code":"PPL",
    "gn:name":"Hacienda Tongolona",
    "gn:population":0,
    "gn:timezone":"America/El_Salvador",
    "iso:country":"SV",
    "name:und_x_variant":[
        "Tangolona",
        "Tongolona",
        "Hacienda Tangolona",
        "Hacienda Tongolona"
    ],
    "wof:name":"Hacienda Tongolona",
    "wof:placetype":"locality"
},
  "geometry": {"coordinates":[-88.25,13.58333],"type":"Point"}
}