{
  "type": "Feature",
  "properties": {
    "gn:admin1_code":"01",
    "gn:asciiname":"Matala",
    "gn:cc2":"SV",
    "gn:country_code":"SV",
    "gn:dem":700,
    "gn:feature_class":"P",
    "gn:feature_code":"PPL",
    "gn:name":"Matala",
    "gn:population":0,
    "gn:timezone":"America/El_Salvador",
    "iso:country":"SV",
    "name:ceb_x_preferred":[
        "Matala"
    ],
    "name:deu_x_preferred":[
        "Matala"
    ],
    "name:fin_x_preferred":[
        "Matala"
    ],
    "name:ita_x_preferred":[
        "Matala"
    ],
    "name:swe_x_preferred":[
        "Matala"
    ],
    "name:und_x_variant":[
        "Caser\u00edo Matala",
        "Matasi"
    ],
    "wof:name":"Matala",
    "wof:placetype":"locality"
},
  "geometry": {"coordinates":[-89.88333,13.81667],"type":"Point"}
}