{
  "type": "Feature",
  "properties": {
    "gn:admin1_code":"09",
    "gn:asciiname":"El Tablon",
    "gn:country_code":"SV",
    "gn:dem":312,
    "gn:feature_class":"P",
    "gn:feature_code":"PPL",
    "gn:name":"El Tabl\u00f3n",
    "gn:population":0,
    "gn:timezone":"America/El_Salvador",
    "iso:country":"SV",
    "wof:name":"El Tablon",
    "wof:placetype":"locality"
},
  "geometry": {"coordinates":[-88.33333,13.83333],"type":"Point"}
}