{
  "type": "Feature",
  "properties": {
    "gn:admin1_code":"09",
    "gn:asciiname":"La Isla",
    "gn:country_code":"SV",
    "gn:dem":77,
    "gn:feature_class":"P",
    "gn:feature_code":"PPL",
    "gn:name":"La Isla",
    "gn:population":0,
    "gn:timezone":"America/El_Salvador",
    "iso:country":"SV",
    "wof:name":"La Isla",
    "wof:placetype":"locality"
},
  "geometry": {"coordinates":[-88.06833,13.29472],"type":"Point"}
}