{
  "type": "Feature",
  "properties": {
    "gn:admin1_code":"10",
    "gn:asciiname":"El Matazano",
    "gn:cc2":"SV",
    "gn:country_code":"SV",
    "gn:dem":308,
    "gn:feature_class":"P",
    "gn:feature_code":"PPL",
    "gn:name":"El Matazano",
    "gn:population":0,
    "gn:timezone":"America/El_Salvador",
    "iso:country":"SV",
    "name:und_x_variant":[
        "Cant\u00f3n Matazano",
        "Cant\u00f3n Matasano",
        "El Matazano"
    ],
    "wof:name":"El Matazano",
    "wof:placetype":"locality"
},
  "geometry": {"coordinates":[-89.21666999999999,14.01667],"type":"Point"}
}