{
  "type": "Feature",
  "properties": {
    "gn:admin1_code":"11.0",
    "gn:asciiname":"Caserio Los Ranchos",
    "gn:country_code":"SV",
    "gn:dem":467,
    "gn:feature_class":"P",
    "gn:feature_code":"PPL",
    "gn:name":"Caser\u00edo Los Ranchos",
    "gn:population":0,
    "gn:timezone":"America/El_Salvador",
    "iso:country":"SV",
    "wof:name":"Caserio Los Ranchos",
    "wof:placetype":"locality"
},
  "geometry": {"coordinates":[-89.50111,14.185],"type":"Point"}
}