{
  "type": "Feature",
  "properties": {
    "gn:admin1_code":"14",
    "gn:asciiname":"Los Canales",
    "gn:cc2":"SV",
    "gn:country_code":"SV",
    "gn:dem":232,
    "gn:feature_class":"P",
    "gn:feature_code":"PPL",
    "gn:name":"Los Ca\u00f1ales",
    "gn:population":0,
    "gn:timezone":"America/El_Salvador",
    "iso:country":"SV",
    "name:und_x_variant":[
        "Canjales",
        "Ca\u00f1ales",
        "Los Ca\u00f1ales"
    ],
    "wof:name":"Los Canales",
    "wof:placetype":"locality"
},
  "geometry": {"coordinates":[-88.61667,13.43333],"type":"Point"}
}