{
  "type": "Feature",
  "properties": {
    "gn:admin1_code":"13",
    "gn:asciiname":"Hacienda Santa Emilia",
    "gn:cc2":"SV",
    "gn:country_code":"SV",
    "gn:dem":125,
    "gn:feature_class":"P",
    "gn:feature_code":"PPL",
    "gn:name":"Hacienda Santa Emilia",
    "gn:population":0,
    "gn:timezone":"America/El_Salvador",
    "iso:country":"SV",
    "name:und_x_variant":[
        "Santa Emilia",
        "Cant\u00f3n Santa Emilia",
        "Hacienda Santa Emilia"
    ],
    "wof:name":"Hacienda Santa Emilia",
    "wof:placetype":"locality"
},
  "geometry": {"coordinates":[-89.76666999999998,13.66667],"type":"Point"}
}