{
  "type": "Feature",
  "properties": {
    "gn:admin1_code":"07",
    "gn:asciiname":"Lajitas",
    "gn:country_code":"SV",
    "gn:dem":858,
    "gn:feature_class":"P",
    "gn:feature_code":"PPL",
    "gn:name":"Lajitas",
    "gn:population":0,
    "gn:timezone":"America/El_Salvador",
    "iso:country":"SV",
    "name:ceb_x_preferred":[
        "Lajitas"
    ],
    "name:swe_x_preferred":[
        "Lajitas"
    ],
    "wof:name":"Lajitas",
    "wof:placetype":"locality"
},
  "geometry": {"coordinates":[-87.81889,13.89139],"type":"Point"}
}