{
  "type": "Feature",
  "properties": {
    "gn:admin1_code":"05",
    "gn:asciiname":"La Shila",
    "gn:cc2":"SV",
    "gn:country_code":"SV",
    "gn:dem":480,
    "gn:feature_class":"P",
    "gn:feature_code":"PPL",
    "gn:name":"La Shila",
    "gn:population":0,
    "gn:timezone":"America/El_Salvador",
    "iso:country":"SV",
    "name:und_x_variant":[
        "Santa Maria",
        "La Chila",
        "Caser\u00edo La Chila",
        "Cant\u00f3n La Shila",
        "La Shila"
    ],
    "wof:name":"La Shila",
    "wof:placetype":"locality"
},
  "geometry": {"coordinates":[-89.34639,13.57083],"type":"Point"}
}