{
  "type": "Feature",
  "properties": {
    "gn:admin1_code":"05",
    "gn:asciiname":"San Benito",
    "gn:country_code":"SV",
    "gn:dem":524,
    "gn:feature_class":"P",
    "gn:feature_code":"PPL",
    "gn:name":"San Benito",
    "gn:population":0,
    "gn:timezone":"America/El_Salvador",
    "iso:country":"SV",
    "wof:name":"San Benito",
    "wof:placetype":"locality"
},
  "geometry": {"coordinates":[-89.53333000000001,13.61667],"type":"Point"}
}