{
  "type": "Feature",
  "properties": {
    "gn:admin1_code":"10",
    "gn:asciiname":"Tutultepeque",
    "gn:cc2":"SV",
    "gn:country_code":"SV",
    "gn:dem":406,
    "gn:feature_class":"P",
    "gn:feature_code":"PPL",
    "gn:name":"Tutultepeque",
    "gn:population":0,
    "gn:timezone":"America/El_Salvador",
    "iso:country":"SV",
    "name:und_x_variant":[
        "Hacienda Tutultepeque",
        "Tultultepeque",
        "Tutultepeque"
    ],
    "wof:name":"Tutultepeque",
    "wof:placetype":"locality"
},
  "geometry": {"coordinates":[-89.22333,13.89389],"type":"Point"}
}