{
  "type": "Feature",
  "properties": {
    "gn:admin1_code":"14",
    "gn:asciiname":"Galingagua",
    "gn:country_code":"SV",
    "gn:dem":391,
    "gn:feature_class":"P",
    "gn:feature_code":"PPL",
    "gn:name":"Galingagua",
    "gn:population":0,
    "gn:timezone":"America/El_Salvador",
    "iso:country":"SV",
    "wof:name":"Galingagua",
    "wof:placetype":"locality"
},
  "geometry": {"coordinates":[-88.58333,13.45],"type":"Point"}
}