{
  "type": "Feature",
  "properties": {
    "gn:admin1_code":"07",
    "gn:asciiname":"El Chichipate",
    "gn:country_code":"SV",
    "gn:dem":122,
    "gn:feature_class":"P",
    "gn:feature_code":"PPL",
    "gn:name":"El Chichipate",
    "gn:population":0,
    "gn:timezone":"America/El_Salvador",
    "iso:country":"SV",
    "wof:name":"El Chichipate",
    "wof:placetype":"locality"
},
  "geometry": {"coordinates":[-88.07306,13.225],"type":"Point"}
}