{
  "type": "Feature",
  "properties": {
    "gn:admin1_code":"14",
    "gn:asciiname":"El Monito",
    "gn:country_code":"SV",
    "gn:dem":417,
    "gn:feature_class":"P",
    "gn:feature_code":"PPL",
    "gn:name":"El Monito",
    "gn:population":0,
    "gn:timezone":"America/El_Salvador",
    "iso:country":"SV",
    "wof:name":"El Monito",
    "wof:placetype":"locality"
},
  "geometry": {"coordinates":[-88.23666999999998,13.23139],"type":"Point"}
}