{
  "type": "Feature",
  "properties": {
    "gn:admin1_code":"06",
    "gn:asciiname":"Las Tablas",
    "gn:country_code":"SV",
    "gn:dem":29,
    "gn:feature_class":"P",
    "gn:feature_code":"PPL",
    "gn:name":"Las Tablas",
    "gn:population":0,
    "gn:timezone":"America/El_Salvador",
    "iso:country":"SV",
    "name:ben_x_preferred":[
        "\u09b2\u09be\u09b8 \u09a4\u09be\u09ac\u09be\u09b2\u09be\u09b8"
    ],
    "name:ceb_x_preferred":[
        "Las Tablas"
    ],
    "name:ell_x_preferred":[
        "\u039b\u03b1\u03c2 \u03a4\u03ac\u03bc\u03c0\u03bb\u03b1\u03c2"
    ],
    "name:fas_x_preferred":[
        "\u0644\u0627\u0633 \u062a\u0627\u0628\u0644\u0627\u0633"
    ],
    "name:heb_x_preferred":[
        "\u05dc\u05d0\u05e1 \u05d8\u05d1\u05dc\u05e1"
    ],
    "name:hin_x_preferred":[
        "\u0932\u093e\u0938 \u0924\u092c\u094d\u0932\u093e\u0938"
    ],
    "name:hun_x_preferred":[
        "Las Tablas"
    ],
    "name:ind_x_preferred":[
        "Las Tablas"
    ],
    "name:ita_x_preferred":[
        "Las Tablas"
    ],
    "name:spa_x_preferred":[
        "Las Tablas"
    ],
    "name:srp_x_preferred":[
        "\u041b\u0430\u0441 \u0422\u0430\u0431\u043b\u0430\u0441"
    ],
    "name:swe_x_preferred":[
        "Las Tablas"
    ],
    "name:tur_x_preferred":[
        "Las Tablas"
    ],
    "name:ukr_x_preferred":[
        "\u041b\u0430\u0441-\u0422\u0430\u0431\u043b\u0430\u0441"
    ],
    "name:vie_x_preferred":[
        "Las Tablas"
    ],
    "wof:name":"Las Tablas",
    "wof:placetype":"locality"
},
  "geometry": {"coordinates":[-88.86667,13.43333],"type":"Point"}
}