{
  "type": "Feature",
  "properties": {
    "gn:admin1_code":"06",
    "gn:asciiname":"Las Tablas",
    "gn:country_code":"SV",
    "gn:dem":29,
    "gn:feature_class":"P",
    "gn:feature_code":"PPL",
    "gn:name":"Las Tablas",
    "gn:population":0,
    "gn:timezone":"America/El_Salvador",
    "iso:country":"SV",
    "name:ceb_x_preferred":[
        "Las Tablas"
    ],
    "name:ita_x_preferred":[
        "Las Tablas"
    ],
    "name:spa_x_preferred":[
        "Las Tablas"
    ],
    "name:srp_x_preferred":[
        "\u041b\u0430\u0441 \u0422\u0430\u0431\u043b\u0430\u0441"
    ],
    "name:swe_x_preferred":[
        "Las Tablas"
    ],
    "wof:name":"Las Tablas",
    "wof:placetype":"locality"
},
  "geometry": {"coordinates":[-88.86667,13.43333],"type":"Point"}
}