{
  "type": "Feature",
  "properties": {
    "iso:country":"SV",
    "name:ceb_x_preferred":[
        "Conchagua"
    ],
    "name:eng_x_preferred":[
        "Conchagua"
    ],
    "name:fra_x_preferred":[
        "Conchagua"
    ],
    "name:ita_x_preferred":[
        "Conchagua"
    ],
    "name:jpn_x_preferred":[
        "\u30b3\u30f3\u30c1\u30e3\u30b0\u30a2"
    ],
    "name:nld_x_preferred":[
        "Conchagua"
    ],
    "name:pol_x_preferred":[
        "Conchagua"
    ],
    "name:por_x_preferred":[
        "Conchagua"
    ],
    "name:spa_x_preferred":[
        "Conchagua"
    ],
    "name:zho_x_preferred":[
        "\u5b54\u67e5\u74dc"
    ],
    "qs:gn_country":"SV",
    "qs:gn_fcode":"PPL",
    "qs:gn_pop":3034,
    "qs:name":"Conchagua",
    "qs:name_adm0":"El Salvador",
    "qs:name_adm1":"La Uni\u00f3n",
    "qs:photos":49,
    "qs:photos_1k":10,
    "qs:photos_9k":1,
    "qs:photos_9r":2,
    "qs:photos_all":49,
    "qs:photos_sr":2,
    "qs:placetype":"Town",
    "qs:pop_sr":"4",
    "qs:woe_adm0":23424807,
    "wof:name":"Conchagua",
    "wof:placetype":"locality",
    "wof:population":3034
},
  "geometry": {"coordinates":[-87.86472000000001,13.30778],"type":"Point"}
}