{
  "type": "Feature",
  "properties": {
    "gn:admin1_code":"09",
    "gn:asciiname":"La Cuesta",
    "gn:country_code":"SV",
    "gn:dem":124,
    "gn:feature_class":"P",
    "gn:feature_code":"PPL",
    "gn:name":"La Cuesta",
    "gn:population":0,
    "gn:timezone":"America/El_Salvador",
    "iso:country":"SV",
    "wof:name":"La Cuesta",
    "wof:placetype":"locality"
},
  "geometry": {"coordinates":[-88.18666999999998,13.44694],"type":"Point"}
}