{
  "type": "Feature",
  "properties": {
    "gn:admin1_code":"13.0",
    "gn:asciiname":"El Zarzalito",
    "gn:country_code":"SV",
    "gn:dem":192,
    "gn:feature_class":"P",
    "gn:feature_code":"PPL",
    "gn:name":"El Zarzalito",
    "gn:population":0,
    "gn:timezone":"America/El_Salvador",
    "iso:country":"SV",
    "wof:name":"El Zarzalito",
    "wof:placetype":"locality"
},
  "geometry": {"coordinates":[-89.81361,13.7025],"type":"Point"}
}