{
  "type": "Feature",
  "properties": {
    "gn:admin1_code":"06",
    "gn:asciiname":"Paredes",
    "gn:cc2":"SV",
    "gn:country_code":"SV",
    "gn:dem":46,
    "gn:feature_class":"P",
    "gn:feature_code":"PPL",
    "gn:name":"Paredes",
    "gn:population":0,
    "gn:timezone":"America/El_Salvador",
    "iso:country":"SV",
    "name:und_x_variant":[
        "Hacienda Paredes",
        "Paredes"
    ],
    "wof:name":"Paredes",
    "wof:placetype":"locality"
},
  "geometry": {"coordinates":[-88.83333,13.45],"type":"Point"}
}