{
  "type": "Feature",
  "properties": {
    "gn:admin1_code":"07",
    "gn:asciiname":"El Mogotillo",
    "gn:cc2":"SV",
    "gn:country_code":"SV",
    "gn:dem":38,
    "gn:feature_class":"P",
    "gn:feature_code":"PPL",
    "gn:name":"El Mogotillo",
    "gn:population":0,
    "gn:timezone":"America/El_Salvador",
    "iso:country":"SV",
    "name:und_x_variant":[
        "Mogotillo",
        "El Mogotillo"
    ],
    "wof:name":"El Mogotillo",
    "wof:placetype":"locality"
},
  "geometry": {"coordinates":[-87.88611,13.43528],"type":"Point"}
}