{
  "type": "Feature",
  "properties": {
    "gn:admin1_code":"07",
    "gn:asciiname":"Cordoncillo",
    "gn:cc2":"SV",
    "gn:country_code":"SV",
    "gn:dem":194,
    "gn:feature_class":"P",
    "gn:feature_code":"PPL",
    "gn:name":"Cordoncillo",
    "gn:population":0,
    "gn:timezone":"America/El_Salvador",
    "iso:country":"SV",
    "name:und_x_variant":[
        "El Cordoncillo",
        "Cordoncillo"
    ],
    "wof:name":"Cordoncillo",
    "wof:placetype":"locality"
},
  "geometry": {"coordinates":[-87.98333000000002,13.46667],"type":"Point"}
}