{
  "type": "Feature",
  "properties": {
    "gn:admin1_code":"02",
    "gn:asciiname":"Rio Grande",
    "gn:country_code":"SV",
    "gn:dem":496,
    "gn:feature_class":"P",
    "gn:feature_code":"PPL",
    "gn:name":"R\u00edo Grande",
    "gn:population":0,
    "gn:timezone":"America/El_Salvador",
    "iso:country":"SV",
    "wof:name":"Rio Grande",
    "wof:placetype":"locality"
},
  "geometry": {"coordinates":[-88.59999999999999,13.85],"type":"Point"}
}