{
  "type": "Feature",
  "properties": {
    "gn:admin1_code":"09",
    "gn:asciiname":"Anchico",
    "gn:cc2":"SV",
    "gn:country_code":"SV",
    "gn:dem":95,
    "gn:feature_class":"P",
    "gn:feature_code":"PPL",
    "gn:name":"Anchico",
    "gn:population":0,
    "gn:timezone":"America/El_Salvador",
    "iso:country":"SV",
    "name:und_x_variant":[
        "Cant\u00f3n Anchico",
        "Anchico"
    ],
    "wof:name":"Anchico",
    "wof:placetype":"locality"
},
  "geometry": {"coordinates":[-88.06083000000002,13.42694],"type":"Point"}
}