{
  "type": "Feature",
  "properties": {
    "gn:admin1_code":"7.0",
    "gn:asciiname":"Plan de La Negra",
    "gn:country_code":"SV",
    "gn:dem":204,
    "gn:feature_class":"P",
    "gn:feature_code":"PPL",
    "gn:name":"Plan de La Negra",
    "gn:population":0,
    "gn:timezone":"America/El_Salvador",
    "iso:country":"SV",
    "wof:name":"Plan de La Negra",
    "wof:placetype":"locality"
},
  "geometry": {"coordinates":[-87.71417,13.20528],"type":"Point"}
}